[
  {
    "title": "골드만삭스와 BNP파리바, 블록체인 결제 회사 프날리티의 신규 자금 조달 주도",
    "originLink": "https://www.reuters.com/technology/goldman-leads-new-funding-fnality-blockchain-payments-firm-2023-11-14/",
    "originBody": "",
    "originSummary": [
      "블록체인 기반 도매 결제 회사인 에프널리티는 골드만삭스와 BNP파리바가 주도한 펀딩 라운드에서 7,770만 파운드(9,590만 달러)의 자금을 조달했습니다.",
      "이 자금은 새로운 디지털 결제 모델을 지원하고 금융 시장 거래에서 결제 시간과 비용을 줄이기 위한 글로벌 유동성 관리 네트워크를 구축하는 데 사용될 것입니다.",
      "에프널리티는 현재 영란은행으로부터 영업을 시작하기 위한 승인을 받고 있으며, 전통 금융과 디지털 금융 간의 격차를 해소하는 것을 목표로 하고 있습니다."
    ],
    "commentBody": "",
    "commentSummary": ["-"],
    "downloadMethod": "",
    "retryCount": 0,
    "time": 1699969737489
  },
  {
    "title": "에프널리티, 골드만삭스 및 BNP파리바로부터 9,500만 달러 규모의 시리즈 B 투자 유치",
    "originLink": "https://www.coindesk.com/markets/2023/11/14/first-mover-americas-goldman-leads-blockchain-firm-fnality-raise-of-95m/",
    "originBody": "",
    "originSummary": [
      "핀테크 회사인 에프널리티는 골드만삭스와 BNP파리바가 주도하는 시리즈 B 펀딩에서 9,500만 달러의 자금을 조달했습니다.",
      "XRP 선물에 투자한 트레이더는 블랙록 상장지수펀드(ETF)에 대한 잘못된 소문으로 인해 726만 달러의 손실을 입었습니다.",
      "미국 판사가 파산한 암호화폐 기업 FTX와 블록파이 간의 소송 절차에 대한 자동 집행정지를 해제하여 두 기업이 청구 소송 합의를 협상할 수 있게 되었습니다."
    ],
    "commentBody": "",
    "commentSummary": [],
    "downloadMethod": "",
    "retryCount": 0,
    "time": 1699969737489
  },
  {
    "title": "웹3 마케팅: 기술적 기능보다 감성적 연결에 우선순위를 두는 마케팅",
    "originLink": "https://cointelegraph.com/innovation-circle/if-blockchain-projects-sold-cars-facts-vs-feelings-in-web3-marketing",
    "originBody": "",
    "originSummary": [
      "이 기사는 웹3.0 분야의 블록체인 및 암호화폐 프로젝트의 마케팅 전략을 분석하여 자동차 산업에서 사용되는 성공적인 브랜딩 기법과 비교합니다.",
      "저자는 기술적 기능에만 집중하기보다는 타깃 고객의 요구와 감성을 충족시키는 것이 중요하다고 강조합니다.",
      "시장 조사를 통해 소비자의 구매 결정을 유도하는 감정적 보상을 파악하고, 친숙하고 신뢰할 수 있는 감정적 반응을 전달하여 고객과 소통하는 데 우선순위를 둘 것을 제안합니다."
    ],
    "commentBody": "",
    "commentSummary": [],
    "downloadMethod": "",
    "retryCount": 0,
    "time": 1699969737489
  },
  {
    "title": "스탠다드차타드, 싱가포르에서 블록체인 사업부 출범, 펀드브릿지 캐피탈과 손잡고 토큰화된 채권 펀드 출시",
    "originLink": "https://asia.nikkei.com/Business/Finance/StanChart-launches-blockchain-unit-eyes-Singapore-bond-fund",
    "originBody": "",
    "originSummary": [
      "스탠다드차타드의 벤처 사업부인 리베라가 싱가포르에 새로운 블록체인 사업부를 출범했습니다.",
      "이 플랫폼은 기관이 블록체인에서 금융 상품을 디지털화하여 중개자에 대한 의존도를 낮추고 잠재적으로 비용을 절감할 수 있도록 지원하는 것을 목표로 합니다.",
      "리베라의 초기 프로젝트는 펀드브리지 캐피탈과 협력하여 토큰화된 싱가포르 달러 국채 펀드를 조성하는 것입니다."
    ],
    "commentBody": "",
    "commentSummary": [],
    "downloadMethod": "",
    "retryCount": 0,
    "time": 1699969737489
  },
  {
    "title": "보야 인터랙티브, 1억 달러 투자 계획으로 암호화폐에 뛰어들다",
    "originLink": "https://blockchain.news/news/boyaa-interactive-advances-into-cryptocurrency-with-a-100-million-acquisition-mandate",
    "originBody": "",
    "originSummary": [
      "홍콩의 게임 개발사 보야 인터랙티브는 웹3.0 환경과의 통합을 위한 전략의 일환으로 암호화폐에 최대 1억 달러를 투자할 계획입니다.",
      "비트코인과 이더를 중심으로 주류 암호화폐와 스테이블코인을 인수할 계획입니다.",
      "보야는 최근 몇 년간 긍정적인 재무 성과로 인해 이 벤처에 대한 좋은 입지를 구축했지만, 변동성이 큰 암호화폐 시장과 관련된 위험을 인식하고 있습니다."
    ],
    "commentBody": "",
    "commentSummary": [],
    "downloadMethod": "",
    "retryCount": 0,
    "time": 1699969737489
  },
  {
    "title": "아르고 블록체인, 채굴 마진 증가 및 부채 감소로 2023년 3분기 호실적 발표",
    "originLink": "https://finance.yahoo.com/news/argo-blockchain-plc-announces-q3-070000594.html",
    "originBody": "",
    "originSummary": [
      "암호화폐 채굴 회사인 아르고 블록체인이 2023년 3분기 실적을 발표했으며, 채굴 마진이 눈에 띄게 상승하고 비용이 감소하여 부채가 감소한 것으로 나타났습니다.",
      "아르고는 분기 동안 370 비트코인을 채굴하여 1,040만 달러의 수익을 창출했습니다.",
      "지속 가능성을 달성하기 위해 비핵심 자산을 매각하고 채굴 작업에 재생 에너지를 활용하는 방안을 고려하고 있습니다."
    ],
    "commentBody": "",
    "commentSummary": [],
    "downloadMethod": "",
    "retryCount": 0,
    "time": 1699969737489
  },
  {
    "title": "애니모카 브랜드, 칠리즈 블록체인 네트워크에 합류하여 웹3 플랫폼에서 스포츠 참여 강화",
    "originLink": "https://www.cointrust.com/market-news/animoca-brands-joins-chiliz-blockchain-network-elevating-web3-sports-engagement",
    "originBody": "",
    "originSummary": [
      "애니모카 브랜드는 칠리즈 블록체인 네트워크의 검증자가 되어 스포츠 업계에서 입지를 넓히고 있습니다.",
      "이 통합을 통해 Animoca 브랜드는 칠리즈 스포츠파이 생태계를 형성하고 스포츠와 웹3.0의 융합에 기여할 수 있게 되었습니다.",
      "애니모카 브랜드는 '모카버스' 프로젝트를 위해 2천만 달러의 투자를 유치하며 메타버스 부문에 대한 노력을 입증하고 블록체인과 스포츠 산업 간의 협업이 증가하고 있음을 강조했습니다."
    ],
    "commentBody": "",
    "commentSummary": [],
    "downloadMethod": "",
    "retryCount": 0,
    "time": 1699969737489
  }
]
