[
  {
    "id": 37199495,
    "title": "クリス・ノーヴァが死去",
    "originLink": "https://nivenly.org/blog/2023/08/19/an-announcement-regarding-kris-n%C3%B3va/",
    "originBody": "",
    "commentLink": "https://news.ycombinator.com/item?id=37199495",
    "commentBody": "",
    "originSummary": [
      "ニブンリーのリーダーであり指導者であったクリス・ノヴァが、プロフェッショナリズムとビジョンの遺産を残し、惜しまれつつこの世を去った。",
      "ニブンリー・コミュニティはクリス・ノーヴァの死を悼み、将来のための次のステップに取り組んでいる。",
      "クリス・ノーヴァの指導と専門知識なしに、ニブンリーのコミュニティがどのように前進していくかは、現時点では不明である。"
    ],
    "commentSummary": [
      "オープンソース業界の著名人であるクリス・ノヴァが、登山中の事故により惜しくも他界した。",
      "彼女は技術業界への貢献とその刺激的な仕事ぶりが認められている。",
      "彼女の死をめぐる言説には、登山のような活動に伴うリスクや、それがもたらす社会的課題についての議論も含まれている。",
      "自閉症患者の社会的スキルや、明確なインクルーシブ・ガイドラインの重要性についての議論がある。",
      "著者は、自閉症の人は社会的スキルを学べないという考え方に反対し、社会的相互作用に対する努力と異なる視点の必要性を強調している。",
      "著者はまた、ウェブサイトで特定の記事に十分な注意が払われていないことにも疑問を呈している。"
    ],
    "points": 803,
    "commentCount": 113,
    "retryCount": 0,
    "time": 1692541831
  },
  {
    "id": 37198954,
    "title": "遠くの物体は拡大して見えるはずではないのか？",
    "originLink": "https://astronomy.stackexchange.com/questions/54499/shouldnt-very-very-distant-objects-appear-magnified",
    "originBody": "",
    "commentLink": "https://news.ycombinator.com/item?id=37198954",
    "commentBody": "",
    "originSummary": [
      "Astronomy Stack Exchangeは、天文学者や天体物理学者がQ&Aを行うためのプラットフォームです。",
      "あるユーザーから、非常に遠くの物体が拡大表示されないのはなぜかという質問があった。",
      "別のユーザーは、特定の距離で顕著になるものの、空間の膨張は拡大を引き起こすと説明している。"
    ],
    "commentSummary": [
      "膨張する宇宙と有限の光速は、遠くの物体が拡大して見える一因となっている。",
      "相対性理論や量子力学といった物理学の概念は、この現象の理解に一役買っている。",
      "光の速度は、因果関係や空間を移動するものの最大速度として議論されている。",
      "宇宙マイクロ波背景は光の限界を示すものであり、それを超える天体はまだ見えていないことを示唆している。",
      "また、宇宙の膨張の証拠や、遠くの天体を観測することの限界についても触れている。"
    ],
    "points": 515,
    "commentCount": 135,
    "retryCount": 0,
    "time": 1692538191
  },
  {
    "id": 37200615,
    "title": "物理学を学ぶ (2021)",
    "originLink": "https://www.susanrigetti.com/physics",
    "originBody": "",
    "commentLink": "https://news.ycombinator.com/item?id=37200615",
    "commentBody": "",
    "originSummary": [
      "スーザン・リゲッティは、読者からのフィードバックを取り入れて改良を加えた、独学で物理を学ぶためのガイドの第2版を発表した。",
      "このガイドでは、微積分から始めて専門分野へと進む、物理学のさまざまな科目を勉強することを勧めている。",
      "また、一般相対性理論や場の量子論のような高度なトピックだけでなく、学部や大学院レベルの物理学の教科書など、より広い視野を持つための一般的な物理学の本も提案している。"
    ],
    "commentSummary": [
      "ディスカッションでは、連続体力学の省略や、水力学や宇宙論モデルのような現象を理解することの重要性など、物理教育におけるさまざまなトピックが取り上げられた。",
      "量子物理学以外の書籍の推薦や、物理学と工学の境界に関する議論も含まれている。",
      "物理学を学ぶ上での数学、特に微積分の重要性や、独学と正規教育の効果について議論されている。"
    ],
    "points": 421,
    "commentCount": 144,
    "retryCount": 0,
    "time": 1692548893
  },
  {
    "id": 37202727,
    "title": "Jazz²の復活：オープンソースJazz Jackrabbit 2再実装",
    "originLink": "http://deat.tk/jazz2/",
    "originBody": "",
    "commentLink": "https://news.ycombinator.com/item?id=37202727",
    "commentBody": "",
    "originSummary": [
      "Jazz² ResurrectionはJazz Jackrabbit 2というゲームをオープンソースで再実装したもので、プレイヤーはクラシックなゲームをモダンなプラットフォームで体験することができます。",
      "このゲームは、Windows、Linux、macOS、Android、Nintendo Switch、ウェブブラウザなど、さまざまなプラットフォームでダウンロードしてプレイできる。",
      "このプロジェクトはGNU General Public License v3.0でライセンスされ、修正されたnCineゲームエンジンを利用しており、多用途でカスタマイズ可能なゲーム体験を提供します。"
    ],
    "commentSummary": [
      "Jazz Jackrabbit 2とそのオープンソースの再実装について、ユーザー同士がディスカッションを行い、ゲームをプレイした経験や思い出を共有します。",
      "参加者からは、似たようなプラットフォーマーを推薦する声が上がり、同じようなレトロゲームを探求することへの関心の高さがうかがえる。",
      "対談は、ゲーム開発、特にマルチプレイヤーサポートを実装する際の課題についての議論に範囲を広げ、放棄ウェアの概念や、さまざまなプラットフォームでのゲームの利用可能性についても触れている。"
    ],
    "points": 376,
    "commentCount": 78,
    "retryCount": 0,
    "time": 1692563879
  },
  {
    "id": 37205731,
    "title": "私たちは皆、一時的な障害者にすぎない",
    "originLink": "https://blog.jim-nielsen.com/2023/temporarily-abled/",
    "originBody": "",
    "commentLink": "https://news.ycombinator.com/item?id=37205731",
    "commentBody": "",
    "originSummary": [
      "著者は休暇中に膝を負傷し、身体能力のはかなさについて考える。",
      "彼らは、回復を助けてくれるアクセシビリティ補助具に感謝の意を表している。",
      "著者は、治療のために必要な休暇を取ることができる仕事を持つことの特権を認めている。"
    ],
    "commentSummary": [
      "この記事では、スターティング・ストレングスのような筋力トレーニング・プログラムの利点と潜在的なリスクを探っている。",
      "自分の体の声に耳を傾け、個々の目標を設定し、激しい筋力トレーニングにおいて長期的な健康と怪我の予防を優先することの重要性を強調している。",
      "対談では、パワーリフティングやボディビルにおけるケガのリスク、マシンとフリーウェイトの使い分け、適切なフォームと優れたコーチングの重要性といったトピックが取り上げられた。"
    ],
    "points": 282,
    "commentCount": 174,
    "retryCount": 0,
    "time": 1692594963
  },
  {
    "id": 37197903,
    "title": "電気地図",
    "originLink": "https://app.electricitymaps.com",
    "originBody": "",
    "commentLink": "https://news.ycombinator.com/item?id=37197903",
    "commentBody": "",
    "originSummary": [
      "このリストは、電力消費の炭素強度に基づいて国や地域をランク付けしており、エネルギー使用が環境に与える影響を示している。",
      "ランキングに使用されたデータは、電力の気候への影響を可視化するオープンソースのプラットフォーム「Electricity Maps」から入手した。",
      "このアプリは情報を提供するだけでなく、ユーザーが自分の地域や国をリストに追加して貢献することもできる。さらに、このアプリは過去のデータを提供し、さまざまな期間における炭素集約度を見ることができる。"
    ],
    "commentSummary": [
      "電力使用量、天気、飛行機や衛星の追跡、鉄道、光害、自然災害などのライブデータを提供するさまざまなウェブサイトがある。",
      "これらのウェブサイトで使用されているデータと情報源の正確性は、重要な論点である。",
      "ドイツの再生可能エネルギーへの移行が取り上げられ、再生可能エネルギーの規模拡大における課題と限界、石炭と輸入電力への依存、そしてそれが期待されたほど成功していないという認識が示されている。"
    ],
    "points": 224,
    "commentCount": 109,
    "retryCount": 0,
    "time": 1692528523
  },
  {
    "id": 37205053,
    "title": "FreeBSD は SYSINT 上で bubblesort を mergesort に置き換えた。",
    "originLink": "https://twitter.com/cperciva/status/1693127769901969772",
    "originBody": "",
    "commentLink": "https://news.ycombinator.com/item?id=37205053",
    "commentBody": "",
    "originSummary": [
      "FreeBSD (HEAD) は、その SYSINIT で bubblesort アルゴリズムを置き換えるために mergesort アルゴリズムを実装しました。",
      "この変更により、スピードが著しく向上した。",
      "マージソートアルゴリズムの採用は、 FreeBSD がそのシステムの性能と効率を向上させるというコミットメントを 表しています。"
    ],
    "commentSummary": [
      "FreeBSD は、仮想マシンのカーネル起動速度を向上させるために、 バブルソート (bubblesort) アルゴリズムをマージソート (mergesort) に置き換えました。",
      "ある開発者は、bubblesort を mergesort に置き換えることで FreeBSD の起動時間を 100 倍高速化しました。",
      "バブルソートを使ったオリジナルの実装で十分だと主張する人もいれば、挿入ソートを使った方がパフォーマンスが上がるという人もいる。"
    ],
    "points": 223,
    "commentCount": 145,
    "retryCount": 0,
    "time": 1692587360
  },
  {
    "id": 37197986,
    "title": "神を信じずとも、悪魔を信じずにはいられない",
    "originLink": "https://www.robkhenderson.com/p/without-belief-in-a-god-but-never",
    "originBody": "",
    "commentLink": "https://news.ycombinator.com/item?id=37197986",
    "commentBody": "",
    "originSummary": [
      "この記事では、エリック・ホッファーの著書『The True Believer』と、大衆運動の背後にある動機を理解する上でのその関連性を探る。",
      "ホッファーは、大衆運動を推進する上でフラストレーションが重要な役割を果たし、大衆運動はメンバーのフラストレーションを意図的に利用すると主張する。",
      "この記事は、二極化した政治と平等の追求が、いかにフラストレーションを募らせ、社会運動の勃興につながるかを浮き彫りにしている。",
      "ホッファーはまた、大衆運動が不満のある個人に目的意識とアイデンティティを提供することも示唆している。",
      "記事はさらに、大衆運動では憎しみがしばしば求心力として使われるというホッファーの観察に触れている。",
      "全体として、この記事は大衆運動の危険性と、個人の不満を操り利用するその能力を強調している。"
    ],
    "commentSummary": [
      "この議論では、大衆運動における明確な目標と敵の存在が与える影響について探る。",
      "参加者は、ソーシャルネットワークやメディアによって引き起こされる二極化、イデオロギーや宗教の影響について議論する。",
      "また、暴力、教育、信念体系の関連性についても、教育と教化の区別とともに探求している。"
    ],
    "points": 217,
    "commentCount": 207,
    "retryCount": 0,
    "time": 1692529355
  },
  {
    "id": 37205029,
    "title": "不安な脳が感情調節をリダイレクト",
    "originLink": "https://www.nature.com/articles/s41467-023-40666-3",
    "originBody": "",
    "commentLink": "https://news.ycombinator.com/item?id=37205029",
    "commentBody": "",
    "originSummary": [
      "不安症患者は、前頭極皮質（FPl）の過剰興奮性を示し、感情制御のために他の前頭皮質領域に依存している。",
      "扁桃体とFPlの間の強い結合は、不安症の人に見られる。",
      "この研究ではまた、不安症患者のFPlではグルタミン酸に対するGABAの比率が高いことも明らかにされており、不安障害への介入の可能性が示唆されている。"
    ],
    "commentSummary": [
      "この対談では、不安と恐怖、そしてそれらに対する脳の反応の関連性について掘り下げていく。",
      "不安に対するさまざまな視点と、薬物療法、セラピー、経頭蓋磁気刺激などの潜在的な治療法について検討する。",
      "マインドフルネスと自己認識は、恐怖と不安を管理するための貴重なテクニックとして認められており、一方で、徐々に恐怖に立ち向かい、不安を軽減するための積極的な手段を講じることが強調されている。"
    ],
    "points": 208,
    "commentCount": 78,
    "retryCount": 0,
    "time": 1692587091
  },
  {
    "id": 37202415,
    "title": "サンフランシスコにあるコダクロームのスライドでいっぱいの廃キャビネット",
    "originLink": "https://petapixel.com/2023/08/16/the-mystery-of-an-abandoned-cabinet-full-of-kodachrome-slides-in-san-francisco/",
    "originBody": "",
    "commentLink": "https://news.ycombinator.com/item?id=37202415",
    "commentBody": "",
    "originSummary": [
      "1960年代のサンフランシスコの魅力的な写真が収められたコダクロームのスライドキャビネットが歩道で発見された。",
      "このスライドでは、ベイエリア高速鉄道の建設と街の日常生活を紹介している。",
      "写真家のジェームズ・マーティンはサンフランシスコに情熱を注いだ学校の教師だった。",
      "現在、さらに2つのキャビネットのスライドが見つかっていない。"
    ],
    "commentSummary": [
      "サンフランシスコの歴史的なプールで泳ぐ人々を撮影した、忘れ去られたコダクロームのスライド・コレクションが、ノスタルジーと好奇心を呼び起こす。",
      "この会話では、オンラインで品物を売ったり譲ったりすることの難しさに焦点が当てられ、代替のプラットフォームが提案された。",
      "コダクロームスライドにまつわる個人的な逸話や、保存やスキャンに関するアドバイスとともに、個人コレクションの適切な受取人を見つけることの意義や、コダックという会社の没落について探求している。"
    ],
    "points": 208,
    "commentCount": 80,
    "retryCount": 0,
    "time": 1692561244
  }
]
