[
  {
    "id": 39326559,
    "title": "সহকর্মীর মৃত্যু নিয়ে কথা বলায় অবৈধভাবে কর্মী ছাঁটাই করল অ্যামাজন",
    "originLink": "https://jacobin.com/2023/11/i-was-illegally-fired-by-amazon-for-speaking-out-about-a-coworkers-death/",
    "originBody": "",
    "commentLink": "https://news.ycombinator.com/item?id=39326559",
    "commentBody": "",
    "originSummary": [
      "পোল্যান্ডের একটি আদালত রায় দিয়েছে যে অ্যামাজন অমানবিক আচরণ, ইউনিয়ন অধিকার লঙ্ঘন এবং বিপজ্জনক কাজের পরিবেশের মতো বিষয়গুলি তুলে ধরে সহকর্মীর মৃত্যুর বিষয়ে কথা বলা একজন কর্মীকে অবৈধভাবে বরখাস্ত করেছে।",
      "আদালত দেখতে পেয়েছে যে অ্যামাজন ইউনিয়ন অধিকার লঙ্ঘন করেছে, তবে সংস্থাটির এখনও তিন সপ্তাহের মধ্যে এই রায়ের বিরুদ্ধে আপিল করার বিকল্প রয়েছে। এই রায়ের ফলে অ্যামাজনে নীতিতে উল্লেখযোগ্য পরিবর্তন আসবে কিনা তা এখনও অনিশ্চিত।",
      "কর্মসংস্থান চুক্তির পার্থক্যের কারণে শ্রমিকরা সংগঠিত হওয়ার ক্ষেত্রে চ্যালেঞ্জের মুখোমুখি হয়, যদিও ইউনিয়ন কর্মকর্তাদের জন্য আইনি সুরক্ষা এবং নতুন সরকারের অধীনে সম্ভাব্য পরিবর্তনের মতো ইতিবাচক উন্নয়ন হয়েছে।"
    ],
    "commentSummary": [
      "পোল্যান্ডে একজন অ্যামাজন কর্মী দাবি করেছেন যে সহকর্মীর মৃত্যুর বিষয়ে কথা বলার জন্য তাকে অবৈধভাবে বরখাস্ত করা হয়েছিল, মার্কিন কর্মীদের বিরুদ্ধে সম্ভাব্য প্রতিশোধের বিষয়ে উদ্বেগ প্রকাশ করেছে।",
      "কথোপকথনটি রাজ্য জুড়ে রাস্তার অবস্থার বৈষম্য, ফ্লোরিডা এবং ক্যালিফোর্নিয়ায় কর ব্যবস্থার পার্থক্য, কর্মক্ষেত্র উদযাপন এবং এইচআর বিভাগের সাথে কর্মীদের অভিজ্ঞতা এবং নিয়োগকর্তা এবং কর্মচারীদের মধ্যে ক্ষমতার গতিশীলতার মতো বিষয়গুলি অন্তর্ভুক্ত করে।",
      "এটি ইউনিয়নকরণের প্রচেষ্টা, অ্যামাজনের লাভজনকতা এবং নিরাপদ কাজের পরিবেশ নিশ্চিত করার জন্য নিয়োগকারীদের বাধ্যবাধকতা সম্পর্কিত আলোচনাগুলিও ছড়িয়ে দেয়।"
    ],
    "points": 528,
    "commentCount": 418,
    "retryCount": 0,
    "time": 1707576993
  },
  {
    "id": 39330797,
    "title": "ওপেনটিটিডি: আলটিমেট ওপেন সোর্স ট্রান্সপোর্ট টাইকুন গেম",
    "originLink": "https://www.openttd.org/about",
    "originBody": "",
    "commentLink": "https://news.ycombinator.com/item?id=39330797",
    "commentBody": "",
    "originSummary": [
      "ওপেনটিটিডি একটি ওপেন সোর্স সিমুলেশন গেম যা নতুন বৈশিষ্ট্যগুলি অন্তর্ভুক্ত করার সময় ক্লাসিক গেম \"ট্রান্সপোর্ট টাইকুন ডিলাক্স\" এর সাথে সাদৃশ্যপূর্ণ।",
      "এটি বৃহত্তর মানচিত্র, 255 জন খেলোয়াড়ের সমন্বিত একটি মাল্টিপ্লেয়ার মোড, উন্নত পাথফাইন্ডিং অ্যালগরিদম এবং পর্যাপ্ত কাস্টমাইজেশন বিকল্প সরবরাহ করে।",
      "গেমটি অ্যাক্সেসযোগ্য, একাধিক ভাষা সমর্থন করে এবং বিভিন্ন ইন্টারফেস বর্ধন বৈশিষ্ট্যযুক্ত। উপরন্তু, এটি বিভিন্ন অপারেটিং সিস্টেমের সাথে সামঞ্জস্যপূর্ণ।"
    ],
    "commentSummary": [
      "ওপেনটিটিডি, একটি পরিবহন সিমুলেশন গেম, তার 20 তম বার্ষিকী উদযাপন করছে এবং একটি বড় রিলিজের জন্য প্রস্তুত হচ্ছে।",
      "খেলোয়াড়রা গেমের তাদের প্রিয় উপাদানগুলি ভাগ করে নিচ্ছে, যেমন বন্ধুদের নাশকতা করা এবং ট্র্যাফিক জ্যাম সৃষ্টি করা, আবার কেউ কেউ মনে করেন যে এতে অসুবিধার অভাব রয়েছে এবং চ্যালেঞ্জগুলি প্রবর্তনের পরামর্শ দেয়।",
      "কথোপকথনটি ফ্যাক্টরিওর মতো অন্যান্য সিমুলেটর গেমগুলির সাথে তুলনা, পাশাপাশি নতুন খেলোয়াড়দের জন্য টিপস এবং আপডেট এবং স্টিমে গেমের প্রাপ্যতা সম্পর্কে আলোচনা করে।"
    ],
    "points": 334,
    "commentCount": 54,
    "retryCount": 0,
    "time": 1707604082
  },
  {
    "id": 39327192,
    "title": "আহো: শিক্ষা এবং বিনোদনের জন্য এডাব্লুকে-তে একটি গিট বাস্তবায়ন",
    "originLink": "https://github.com/djanderson/aho",
    "originBody": "",
    "commentLink": "https://news.ycombinator.com/item?id=39327192",
    "commentBody": "",
    "originSummary": [
      "\"আহো\" একটি গিট বাস্তবায়ন যা এডাব্লুকে-তে লেখা, বিনোদন এবং শিক্ষামূলক উদ্দেশ্যে ডিজাইন করা হয়েছে।",
      "এটি গিটের অভ্যন্তরীণগুলি অন্বেষণ করে এবং জিএনইউ এডাব্লুকে এর নতুন বৈশিষ্ট্যগুলি ব্যবহার করে।",
      "প্রকল্পটি চালানোর জন্য নির্দেশাবলী পাওয়া যায় তবে এটি বিএসডি / ম্যাকের উপর মসৃণভাবে কাজ নাও করতে পারে।"
    ],
    "commentSummary": [
      "হ্যাকার নিউজের আলোচনাটি প্রোগ্রামিং ভাষা অক এবং পার্ল, পাইথন এবং রুবির তুলনায় এর সুবিধাগুলি ঘিরে কেন্দ্রীভূত।",
      "অংশগ্রহণকারীরা আউকের সুবিধা হিসাবে নির্ভরতার বিষয়গুলির সরলতা এবং অনুপস্থিতি তুলে ধরেন, তবে জটিল কাজের জন্য এর উপযুক্ততা সম্পর্কে উদ্বেগ রয়েছে।",
      "কথোপকথনের অন্যান্য বিষয়গুলির মধ্যে রয়েছে এওকে আপডেটের অভাব, উন্নতির জন্য পরামর্শ, লিনাক্স কমান্ড লাইন পরিবেশে এর ব্যবহার, পাঠ্য প্রক্রিয়াকরণ এবং সীমিত-মেমরি রাউটারগুলিতে এর দক্ষতা।"
    ],
    "points": 240,
    "commentCount": 104,
    "retryCount": 0,
    "time": 1707581137
  },
  {
    "id": 39327734,
    "title": "কিভাবে কার্যকরভাবে অধ্যয়ন করবেন: সাফল্যের জন্য একটি বিস্তৃত গাইড",
    "originLink": "https://cse.buffalo.edu/~rapaport/howtostudy.html",
    "originBody": "",
    "commentLink": "https://news.ycombinator.com/item?id=39327734",
    "commentBody": "",
    "originSummary": [
      "নিবন্ধটি কার্যকর অধ্যয়নের জন্য একটি পুঙ্খানুপুঙ্খ গাইড সরবরাহ করে, সময় পরিচালনা, নোট গ্রহণ, সক্রিয় পড়া, হোমওয়ার্ক, পরীক্ষার প্রস্তুতি, গবেষণা এবং প্রবন্ধ লেখার মতো বিভিন্ন দিককে সম্বোধন করে।",
      "এটি ব্যক্তিগতকৃত অধ্যয়নের কৌশলগুলি আবিষ্কারের তাত্পর্য তুলে ধরে এবং ব্যক্তিগত অভিজ্ঞতার উপর ভিত্তি করে ব্যবহারিক টিপস সরবরাহ করে।",
      "নিবন্ধটি শেখার শৈলী সম্পর্কিত তত্ত্বগুলিও অস্বীকার করে এবং কার্যকর পড়া, শিক্ষকদের কাছ থেকে সহায়তা চাওয়া এবং পরীক্ষার প্রস্তুতির বিষয়ে অতিরিক্ত সংস্থানগুলির রেফারেন্স সরবরাহ করে।"
    ],
    "commentSummary": [
      "আলোচনাটি নোট নেওয়া এবং বিষয়বস্তু বোঝার মধ্যে বিতর্ক সহ কার্যকর অধ্যয়নের কৌশলগুলি অন্বেষণ করে।",
      "বিভিন্ন শেখার শৈলী এবং প্রেরণার গুরুত্ব নিয়ে আলোচনা করা হয়, পাশাপাশি বিভিন্ন শেখার কৌশল নিয়ে আলোচনা করা হয়।",
      "পাঠ্যটি স্যাট পরীক্ষার পারফরম্যান্সের উন্নতি, দীর্ঘমেয়াদী শেখার ক্ষেত্রে অনুপ্রেরণার ভূমিকা এবং স্মৃতি ধরে রাখার ক্ষেত্রে এনকোডিং এবং পুনরুদ্ধারের গুরুত্বকেও স্পর্শ করে।"
    ],
    "points": 220,
    "commentCount": 71,
    "retryCount": 0,
    "time": 1707583830
  },
  {
    "id": 39327113,
    "title": "Svelte: শীতল জিনিস তৈরির জন্য একটি যাদুকর, ব্যবহারকারী-কেন্দ্রিক ওয়েব ফ্রেমওয়ার্ক",
    "originLink": "https://github.com/sveltejs/svelte/discussions/10085",
    "originBody": "",
    "commentLink": "https://news.ycombinator.com/item?id=39327113",
    "commentBody": "",
    "originSummary": [
      "Svelte একটি ওয়েব ফ্রেমওয়ার্ক যা ওয়েবকে মূল্য দেয় এবং জনপ্রিয়তা তাড়া করার পরিবর্তে ইতিবাচক অভিজ্ঞতার জন্য অপ্টিমাইজ করার দিকে মনোনিবেশ করে।",
      "স্ভেল্ট ইউজার ইন্টারফেস বর্ণনা করার জন্য এইচটিএমএলকে প্রধান ভাষা হিসাবে অগ্রাধিকার দেয় এবং ওয়েব ডেভেলপমেন্টে অগ্রগতি এবং উদ্ভাবনকে উত্সাহ দেয়।",
      "ফ্রেমওয়ার্কটি গুণগত নকশার উপর জোর দেয়, যার লক্ষ্য স্ভেল্টকে যাদুকরী বোধ করা এবং ব্যবহারকারীদের ব্যাপক প্রযুক্তিগত জ্ঞান ছাড়াই শীতল জিনিস তৈরি করতে ক্ষমতায়ন করা। এটি সম্প্রদায়-চালিত, ঐকমত্য এবং প্রতিক্রিয়াকে মূল্য দেয় এবং যে কোনও ধরণের অ্যাপ্লিকেশনের জন্য সর্বোত্তম কাঠামো হওয়ার লক্ষ্য রাখে।"
    ],
    "commentSummary": [
      "Svelte ফ্রেমওয়ার্ক নিয়ে আলোচনা করা হচ্ছে এবং এর শক্তি এবং দুর্বলতা সম্পর্কে ব্যবহারকারীদের বিভিন্ন মতামত রয়েছে।",
      "কিছু ব্যবহারকারী এটি পছন্দ করেন কারণ এটি এইচটিএমএলের সাথে সাদৃশ্যপূর্ণ এবং ব্যবহারকারী-বান্ধব, অন্যরা এইচটিএমএল থেকে বিপথগামী হওয়ার জন্য এবং জটিলতা যুক্ত করার জন্য এটির সমালোচনা করে।",
      "বিতর্কগুলির মধ্যে ইউআই বর্ণনার জন্য এইচটিএমএল বনাম বিকল্প ভাষা ব্যবহারের উপকারিতা এবং কনস, গতিশীল ইন্টারফেসের জন্য এইচটিএমএলের সীমাবদ্ধতা এবং অন্তর্নিহিত প্রযুক্তিগুলি বোঝার তাত্পর্য অন্তর্ভুক্ত রয়েছে। রিঅ্যাক্ট, নেক্সটজেএস এবং ভ্যুর মতো অন্যান্য ফ্রেমওয়ার্কের সাথে তুলনা করা হয় এবং সিনট্যাক্স, কম্পাইলার নির্দেশাবলী এবং পারফরম্যান্স অপ্টিমাইজেশান এবং ব্যবহারকারীর অভিজ্ঞতার উপর আলোচনা করা হয়।"
    ],
    "points": 186,
    "commentCount": 131,
    "retryCount": 0,
    "time": 1707580662
  },
  {
    "id": 39331771,
    "title": "স্কুল ও গির্জাকে টার্গেট করে সোয়াটিং সার্ভিস চালানোর অভিযোগে কিশোরের সন্দেহ হাজার হাজার",
    "originLink": "https://www.independent.co.uk/news/world/americas/crime/swatting-nikki-haley-trump-fbi-stalkers-b2494097.html",
    "originBody": "",
    "commentLink": "https://news.ycombinator.com/item?id=39331771",
    "commentBody": "",
    "originSummary": [
      "ক্যালিফোর্নিয়ার এক কিশোর, অ্যালান উইনস্টন ফিলিয়ন, এনক্রিপ্টেড মেসেজিং অ্যাপ টেলিগ্রামের মাধ্যমে একটি \"সোয়াটিং\" পরিষেবা পরিচালনা করে, বোমা হামলার হুমকি এবং গণ শুটিংয়ের প্রস্তাব দেয় বলে সন্দেহ করা হয়।",
      "ফিলিয়ন এই জাল কলগুলির মাধ্যমে স্কুল, গীর্জা এবং এমনকি সুপ্রিম কোর্টকে টার্গেট করেছিল, হাজার হাজার লোকের জন্য মারাত্মক ঝুঁকি তৈরি করেছিল।",
      "লেখক প্যাট্রিক এস টমলিনসন, যিনি একাধিক সোয়াটিং ঘটনায় শিকার হয়েছিলেন, তিনি কঠোর আইন প্রণয়নের পক্ষে এবং সোয়াটারদের দেশীয় সন্ত্রাসী হিসাবে বিবেচনা করার পক্ষে ছিলেন।"
    ],
    "commentSummary": [
      "আলোচনাগুলি পুলিশের প্রতিক্রিয়া, জবাবদিহিতা এবং প্রশিক্ষণের মতো বিষয়গুলি সহ সোয়াটিংয়ের উপর দৃষ্টি নিবদ্ধ করে।",
      "ভুক্তভোগী এবং পুলিশ কর্মকর্তাদের বিপদ সম্পর্কে উদ্বেগ উত্থাপিত হয়।",
      "প্রস্তাবিত সমাধানগুলির মধ্যে সোয়াটারদের জন্য কঠোর জরিমানা এবং সোয়াট দল পাঠানোর আগে বৈধতা পদ্ধতি উন্নত করা অন্তর্ভুক্ত রয়েছে।"
    ],
    "points": 171,
    "commentCount": 276,
    "retryCount": 0,
    "time": 1707613182
  },
  {
    "id": 39326675,
    "title": "এনওয়াইসিতে ভাড়া-স্থিতিশীল 1 শয়নকক্ষ: উচ্চ ব্রোকার ফি সামর্থ্যের হুমকি দেয়",
    "originLink": "https://gothamist.com/news/a-rent-stabilized-1-bedroom-apartment-for-1100-in-nyc-the-brokers-fee-is-15k",
    "originBody": "",
    "commentLink": "https://news.ycombinator.com/item?id=39326675",
    "commentBody": "",
    "originSummary": [
      "নিউ ইয়র্কের কুইন্সের একটি ব্রোকার এক বেডরুমের অ্যাপার্টমেন্টকে মাসে 1,100 ডলারে বাজারের হারের নীচে তালিকাভুক্ত করেছে, তবে 15,000 ডলার ব্রোকার ফি সহ, অগ্রিম নগদ প্রয়োজনীয়তার কারণে ভাড়াটেদের ভাড়া নেওয়া চ্যালেঞ্জিং করে তোলে।",
      "নিউইয়র্ক সিটির রিয়েল এস্টেট বাজারে অত্যধিক ব্রোকার ফি স্থানান্তরিত করতে চায় এমন ভাড়াটেদের জন্য অসুবিধা সৃষ্টি করছে।",
      "একটি নতুন সিটি কাউন্সিল বিল প্রস্তাব করা হয়েছে যা দালালকে ভাড়া করা পক্ষের ভাড়াটে থেকে ব্রোকার ফি প্রদানের দায়িত্ব স্থানান্তরিত করবে, তবে সমালোচকরা যুক্তি দেখান যে এটি উচ্চতর ভাড়া হতে পারে।"
    ],
    "commentSummary": [
      "আলোচনায় বিভিন্ন আবাসন সম্পর্কিত বিষয় যেমন ভাড়ার দাম, সম্পত্তি কর, আবাসন সামর্থ্য এবং ভাড়া দেওয়ার ক্ষেত্রে ক্রেডিট ইতিহাসের ভূমিকা অন্তর্ভুক্ত রয়েছে।",
      "বিভিন্ন দেশ ও শহরের সুনির্দিষ্ট বিষয় উল্লেখ করা হয়, যেমন জার্মানিতে আবাসন সংকট এবং যুক্তরাষ্ট্রে দালাল ফি।",
      "কথোপকথনটি আবাসনকে ঘিরে চ্যালেঞ্জ এবং বিভিন্ন দৃষ্টিভঙ্গির উপর জোর দেয় এবং ন্যায্য এবং সাশ্রয়ী মূল্যের আবাসনের গুরুত্বের উপর জোর দেয়।"
    ],
    "points": 165,
    "commentCount": 389,
    "retryCount": 0,
    "time": 1707577945
  },
  {
    "id": 39328007,
    "title": "অন্ধকূপ মাস্টার হয়ে ওঠা: সহায়তা প্রকৌশলীদের জন্য একটি স্টার্টআপের উদ্ভাবনী সাক্ষাত্কার প্রক্রিয়া",
    "originLink": "https://www.propelauth.com/post/interview-dungeon-master",
    "originBody": "",
    "commentLink": "https://news.ycombinator.com/item?id=39328007",
    "commentBody": "",
    "originSummary": [
      "একটি স্টার্টআপ সহায়তা প্রকৌশলীদের জন্য একটি অনন্য সাক্ষাত্কার প্রক্রিয়া তৈরি করেছে যা কাজের প্রতিদিনের কাজগুলির অনুরূপ একটি সিমুলেটেড পরিবেশ জড়িত।",
      "প্রার্থীদের একটি জাল পণ্য, ডকুমেন্টেশন এবং ইমেল / প্রশ্নের একটি সারি উপস্থাপন করা হয় এবং বাস্তব জীবনে টিকিটগুলি সমাধান করার দায়িত্ব দেওয়া হয়।",
      "প্রক্রিয়াটিতে পিছনে পিছনে যোগাযোগ ছাড়াই সমস্যাগুলি সমাধানের অনুকরণ করার জন্য প্রতিটি টিকিটের জন্য অতিরিক্ত সম্পদ অন্তর্ভুক্ত রয়েছে, অন্ধকূপ এবং ড্রাগনগুলিতে অন্ধকূপ মাস্টার হওয়ার মতো।",
      "সিমুলেশন প্রার্থীদের সমস্যা সমাধানের দক্ষতার মূল্যায়ন করতে সহায়তা করে এবং তাদের দক্ষতার মধ্যে মূল্যবান অন্তর্দৃষ্টি সরবরাহ করে।",
      "তবে, প্রার্থীদের জন্য সীমানা নির্ধারণ এবং সাক্ষাত্কারকারীদের মধ্যে ধারাবাহিকতা নিশ্চিত করার ক্ষেত্রে চ্যালেঞ্জ রয়েছে।",
      "সামগ্রিকভাবে, এই সাক্ষাত্কার প্রক্রিয়াটি ইতিবাচক প্রতিক্রিয়া পেয়েছে এবং প্রার্থীদের জন্য আরও আকর্ষক অভিজ্ঞতা সরবরাহ করে।"
    ],
    "commentSummary": [
      "সফটওয়্যার ইঞ্জিনিয়ারদের জন্য সাক্ষাত্কার প্রক্রিয়ায় একটি পরিবর্তন রয়েছে, বাস্তব-বিশ্বের অভিজ্ঞতার পরিবর্তে অ্যালগরিদমিক প্রশ্নগুলির উপর জোর দেওয়া হয়েছে।",
      "অভিজ্ঞ প্রার্থীরা এই ধরণের প্রশ্নের জন্য প্রস্তুত করতে লড়াই করতে পারে, যার ফলে ন্যায্যতা সম্পর্কে উদ্বেগ দেখা দেয়।",
      "আলোচনার অন্যান্য বিষয়গুলির মধ্যে রয়েছে বড় প্রযুক্তি সংস্থাগুলির প্রভাব, লিটকোড-স্টাইলের প্রশ্নের ব্যবহার, ব্যবহারিক দক্ষতা মূল্যায়নের সীমাবদ্ধতা এবং উন্নত সরঞ্জামগুলিতে অ্যাক্সেসের উপর অর্থনৈতিক ব্যবস্থার প্রভাব।",
      "টেক-হোম অ্যাসাইনমেন্ট এবং মানসম্মত সাক্ষাত্কারের মতো বিভিন্ন সাক্ষাত্কার পদ্ধতির কার্যকারিতা ডেটা তৈরি এবং একাধিক পর্যালোচককে জড়িত করার গুরুত্বের পাশাপাশি বিতর্কিত হয়।",
      "সফটওয়্যার ডেভেলপারদের জন্য কার্যকর নিয়োগ কৌশলগুলি নিয়ে আলোচনা করা হয়, যার মধ্যে রয়েছে কাজের প্রয়োজনীয়তা সংজ্ঞায়িত করা, প্রাসঙ্গিক প্রশ্ন জিজ্ঞাসা করা, কৌতূহল এবং উত্সাহের মূল্যায়ন করা এবং প্রতিযোগিতামূলক বেতন প্রদান করা।"
    ],
    "points": 160,
    "commentCount": 137,
    "retryCount": 0,
    "time": 1707585199
  },
  {
    "id": 39326201,
    "title": "ওয়ালমার্ট, ডেল্টা এবং স্টারবাকস কর্মচারী বার্তাগুলি নিরীক্ষণের জন্য এআই নিয়োগ করে",
    "originLink": "https://www.cnbc.com/2024/02/09/ai-might-be-reading-your-slack-teams-messages-using-tech-from-aware.html",
    "originBody": "",
    "commentLink": "https://news.ycombinator.com/item?id=39326201",
    "commentBody": "",
    "originSummary": [
      "ওয়ালমার্ট, ডেল্টা, শেভরন, টি-মোবাইল এবং স্টারবাকস স্ল্যাক এবং মাইক্রোসফ্ট টিমসের মতো প্ল্যাটফর্মগুলিতে কর্মীদের বার্তাগুলি পর্যবেক্ষণ করতে স্টার্টআপ অ্যাওয়ারের এআই প্রযুক্তি ব্যবহার করছে।",
      "অ্যাওয়ারের এআই প্রযুক্তি কর্মচারীদের অনুভূতি বিশ্লেষণ করে এবং হয়রানি এবং অসম্মতির মতো আচরণগুলি সনাক্ত করে।",
      "অ্যাওয়ারের রাজস্ব বার্ষিক 150% বৃদ্ধি পেয়েছে এবং এর ক্লায়েন্টদের মধ্যে প্রায় 30,000 কর্মচারী সহ বড় সংস্থাগুলি অন্তর্ভুক্ত রয়েছে।"
    ],
    "commentSummary": [
      "ওয়ালমার্ট, ডেল্টা এবং স্টারবাকসের মতো সংস্থাগুলি কর্মীদের বার্তাগুলি পর্যবেক্ষণ করতে এআই প্রযুক্তি ব্যবহার করছে, গোপনীয়তা এবং কর্মীদের উপর কর্পোরেট নিয়ন্ত্রণ সম্পর্কে উদ্বেগ ছড়িয়ে দিচ্ছে।",
      "বিতর্কটি নিপীড়নমূলক কাজের পরিবেশ, সামাজিক আস্থা হ্রাস, গোপনীয়তা আইনের প্রয়োজনীয়তা এবং নজরদারি অনুশীলনের নৈতিক প্রভাব সম্পর্কে প্রশ্ন উত্থাপন করে।",
      "আলোচনায় বার্তাগুলির ম্যানুয়াল এনক্রিপশন, অনুভূতি বিশ্লেষণের সুবিধা এবং ঝুঁকি এবং নিয়োগকর্তাদের দ্বারা ব্যক্তিগত তথ্যের সম্ভাব্য অপব্যবহারের মতো বিষয়গুলিও অন্তর্ভুক্ত রয়েছে। কর্মক্ষেত্রে গোপনীয়তার গুরুত্ব, সম্ভাব্য বয়স বৈষম্য এবং তরুণ বয়সীদের লক্ষ্য করে কৌশলগুলিও উল্লেখ করা হয়েছে।"
    ],
    "points": 148,
    "commentCount": 84,
    "retryCount": 0,
    "time": 1707573991
  },
  {
    "id": 39333220,
    "title": "গিটল্যাবে কাজ করা: পারফরম্যান্স, পরিচালনা এবং অগ্রাধিকারের অভিজ্ঞতার মিশ্রণ",
    "originLink": "https://yorickpeterse.com/articles/what-it-was-like-working-for-gitlab/",
    "originBody": "",
    "commentLink": "https://news.ycombinator.com/item?id=39333220",
    "commentBody": "",
    "originSummary": [
      "লেখক ছয় বছর ধরে গিটল্যাবে কাজ করেছেন এবং সম্প্রতি তাদের অভিজ্ঞতা এবং অন্তর্দৃষ্টি ভাগ করে নিয়েছেন।",
      "তারা কর্মক্ষমতা উন্নত করা, সরঞ্জাম তৈরি করা এবং সংস্থায় নতুন বৈশিষ্ট্য প্রবর্তনের মতো অর্জনগুলি নিয়ে আলোচনা করে।",
      "চ্যালেঞ্জগুলির মুখোমুখি হওয়া চ্যালেঞ্জগুলির মধ্যে রয়েছে পরিচালনার সমস্যা, দুর্বল পারফরম্যান্স এবং বিভিন্ন দিকনির্দেশনা, যা তাদের চলে যেতে পরিচালিত করেছিল।",
      "গিটল্যাবের সিদ্ধান্ত গ্রহণ প্রক্রিয়া এবং পণ্যের সিদ্ধান্তকে অগ্রাধিকার দেওয়া নিয়ে সমালোচনা করা হয়।",
      "নিবন্ধটি সাস বনাম স্ব-হোস্টেড ইনস্টলেশনগুলির চ্যালেঞ্জগুলি তুলে ধরে এবং দ্রুত কোড স্থাপনার গুরুত্বের উপর জোর দেয়।",
      "লেখক গিটল্যাবে তাদের সময়ের একটি মিশ্র পর্যালোচনা দিয়ে শেষ করেছেন, এটি কাজ করার জন্য একটি ভাল জায়গা হিসাবে সুপারিশ করেছেন।"
    ],
    "commentSummary": [
      "আলোচনায় প্রোগ্রামিং ভাষা, ব্যবস্থাপনা, বার্নআউট, অবস্থানের ভিত্তিতে বেতন এবং স্থানীয় অর্থনীতিতে প্রভাব সহ বিভিন্ন বিষয় অন্তর্ভুক্ত রয়েছে।",
      "ভাষা এবং কাঠামোর উপযুক্ততা, ভাল পরিচালনার গুরুত্ব, দূরবর্তী কাজের চ্যালেঞ্জ এবং অবস্থান-ভিত্তিক বেতনের ন্যায্যতা সম্পর্কে বিতর্ক রয়েছে।",
      "নিবন্ধটি পরামর্শ দেয় যে সংস্থাগুলির ক্ষতিপূরণের জন্য একটি মানসম্মত সূত্র থাকা উচিত, সাংগঠনিক সাফল্যের জন্য ভাগ করা এবং স্থাপনার সময়ের মতো বিষয়গুলি বিবেচনা করে।"
    ],
    "points": 142,
    "commentCount": 102,
    "retryCount": 0,
    "time": 1707636544
  },
  {
    "id": 39330330,
    "title": "ডেমোসিন এবং ভিডিও গেম সংগীত স্ট্রিমিং রেডিও স্টেশনগুলির সংকলন",
    "originLink": "https://mw.rat.bz/davgmsrl/",
    "originBody": "",
    "commentLink": "https://news.ycombinator.com/item?id=39330330",
    "commentBody": "",
    "originSummary": [
      "এই ওয়েব পৃষ্ঠাটি ডেমোসিন এবং ভিডিও গেম সঙ্গীত স্ট্রিমিং রেডিও স্টেশন লিঙ্কগুলির সংকলন।",
      "তালিকায় প্রতিটি স্টেশনের জন্য হোমপেজ, প্লেলিস্ট এবং স্ট্রিমগুলির লিঙ্ক অন্তর্ভুক্ত রয়েছে।",
      "ব্যবহারকারীরা অনুরূপ স্টেশনগুলি খুঁজে পেতে জেনার বা কীওয়ার্ড দ্বারা অনুসন্ধান করতে পারেন।"
    ],
    "commentSummary": [
      "পোস্টটি ব্যবহারকারীদের দ্বারা ভাগ করা বিভিন্ন ডেমোসিন এবং ভিডিও গেম সংগীত স্ট্রিমিং রেডিও লিঙ্কগুলি প্রদর্শন করে, উত্সাহীদের জন্য সংস্থানগুলির সংগ্রহ সরবরাহ করে।",
      "Rainwave.cc তার অনন্য বৈশিষ্ট্যের জন্য হাইলাইট করা হয়েছে যা শ্রোতাদের একটি ভোটিং সিস্টেমের মাধ্যমে গান নির্বাচনকে প্রভাবিত করতে সক্ষম করে।",
      "ব্যবহারকারীরা ডেমোসিন এবং ভিডিও গেম সঙ্গীত সম্পর্কিত অন্যান্য ওয়েবসাইট এবং রেডিও স্টেশনগুলিও ভাগ করে নেয়, আগ্রহী ব্যক্তিদের জন্য বিকল্পগুলির পরিসীমা প্রসারিত করে।"
    ],
    "points": 134,
    "commentCount": 32,
    "retryCount": 0,
    "time": 1707599959
  },
  {
    "id": 39326092,
    "title": "ভেরিসাইন থেকে ক্লাউডফ্লেয়ারে .গভ টিএলডি রূপান্তর: অনন্য ডিএনএসএসইসি স্বাক্ষর পদ্ধতি ব্যবহৃত হয়েছে",
    "originLink": "https://indico.dns-oarc.net/event/48/contributions/1038/",
    "originBody": "",
    "commentLink": "https://news.ycombinator.com/item?id=39326092",
    "commentBody": "",
    "originSummary": [
      "উপস্থাপনাটি ভেরিসাইন থেকে ক্লাউডফ্লেয়ারে .গভ শীর্ষ-স্তরের ডোমেনের রূপান্তর এবং ডিএনএসএসইসি স্বাক্ষরের ক্ষেত্রে তাদের পদ্ধতির বিষয়ে আলোচনা করেছে।",
      "ভেরিসাইন আরএসএ এবং এনএসইসি 3 এর সাথে অফলাইন স্বাক্ষর ব্যবহার করেছিল, যখন ক্লাউডফ্লেয়ার ইসিডিএসএ এবং এনএসইসির সাথে অনলাইন স্বাক্ষর ব্যবহার করেছিল।",
      "ব্যাপক পরীক্ষায় এনএসইসি এবং এনএসইসি 3 উভয়ই একই সাথে ব্যবহারে কোনও সমস্যা পাওয়া যায়নি, যার ফলে রূপান্তরটিতে তাদের ব্যবহার হয়।"
    ],
    "commentSummary": [
      "ভেরিসাইন .গভ শীর্ষ-স্তরের ডোমেনের জন্য অপারেশনগুলি ক্লাউডফ্লেয়ারে স্থানান্তরিত করেছে, যা ডিএনএস জটিলতা এবং .এনজেড ডোমেনের ডাউনটাইম সম্পর্কে আলোচনার সূত্রপাত করেছে।",
      "ক্লাউডফ্লেয়ারের সাথে সরকারী অংশীদারিত্ব, সম্ভাব্য এনএসএ নজরদারি এবং ডিএনএস সার্ভার পরিচালনা এবং ক্যাপচা ঘিরে বিভ্রান্তি সম্পর্কে জল্পনা দেখা দেয়।",
      "এই পদক্ষেপটি ক্লাউডফ্লেয়ারের মূল্য প্রস্তাব এবং সমালোচনামূলক ইন্টারনেট অবকাঠামো পরিচালনায় এর ভূমিকা সম্পর্কে প্রশ্ন উত্থাপন করে।"
    ],
    "points": 127,
    "commentCount": 66,
    "retryCount": 0,
    "time": 1707572788
  },
  {
    "id": 39331383,
    "title": "ওয়েব এমআইডিআই এপিআই দিয়ে রিমোট পিয়ানো পাঠগুলি সহজ করা হয়েছে",
    "originLink": "https://keyboardconnect.com/",
    "originBody": "",
    "commentLink": "https://news.ycombinator.com/item?id=39331383",
    "commentBody": "",
    "originSummary": [
      "একজন ডেভেলপার স্কাইপ বা জুমের মতো প্ল্যাটফর্ম ব্যবহার করে পিয়ানো টিউটর এবং শিক্ষার্থীদের মুখোমুখি হওয়া সমস্যাগুলি সমাধান করার জন্য বিশেষভাবে পিয়ানো পাঠের জন্য ডিজাইন করা একটি ভিডিও কনফারেন্স অ্যাপ্লিকেশন তৈরি করছেন।",
      "অ্যাপ্লিকেশনটি মিডিয়া, এমআইডিআই স্টেট এবং শেষ পর্যন্ত শীট মিউজিক ফাইল এবং অন্যান্য বাদ্যযন্ত্র ডেটা সহ ডেটা সংক্রমণের জন্য ওয়েবআরটিটিসি ব্যবহার করে।",
      "অ্যাপ্লিকেশনটির ন্যূনতম টেকসই পণ্য (এমভিপি) প্রত্যাশার চেয়ে ভাল পারফর্ম করেছে এবং বিকাশকারী প্রতিক্রিয়া এবং পরামর্শের জন্য উন্মুক্ত।"
    ],
    "commentSummary": [
      "কীবোর্ড কানেক্ট ওয়েব এমআইডিআই এপিআই ব্যবহার করে দূরবর্তী পিয়ানো পাঠের জন্য একটি সফল প্ল্যাটফর্ম।",
      "ব্যবহারকারীরা পাঠের জন্য সাইন আপ করতে এবং একটি প্রস্তাবিত ইউএসবি এমআইডিআই অ্যাডাপ্টার কিনতে পারেন।",
      "আলোচনাটি পিয়ানো শেখার ক্ষেত্রে ওজনযুক্ত কীগুলির তাত্পর্যের পাশাপাশি কীবোর্ড এবং এমআইডিআই ইন্টারফেসের মতো বিকল্পগুলি অন্বেষণ করে।"
    ],
    "points": 123,
    "commentCount": 55,
    "retryCount": 0,
    "time": 1707609029
  },
  {
    "id": 39325700,
    "title": "ভালোবাসা দিবসে সম্পর্ক বাড়ানোর ৭টি টিপস",
    "originLink": "https://www.psychologytoday.com/gb/blog/beautiful-minds/200812/the-tears-clown",
    "originBody": "",
    "commentLink": "https://news.ycombinator.com/item?id=39325700",
    "commentBody": "",
    "originSummary": [
      "ভ্যালেন্টাইনস ডে-তে সম্পর্ক মজবুত করার সাতটি টিপস দেওয়া হয়েছে এই লেখায়।",
      "এই টিপসগুলি ব্যক্তিদের তাদের অংশীদারদের সাথে তাদের বন্ধন উন্নত করতে এবং উন্নত করতে সহায়তা করতে পারে।",
      "নিবন্ধটি ব্যবহারিক পরামর্শ এবং পরামর্শ সরবরাহ করে যা আরও অর্থবহ এবং উপভোগ্য ভালোবাসা দিবসের অভিজ্ঞতা তৈরি করতে প্রয়োগ করা যেতে পারে।"
    ],
    "commentSummary": [
      "আলোচনাটি কৌতুক, হাস্যরস এবং অসুখী সম্পর্কিত বিস্তৃত বিষয়কে কভার করে।",
      "এটি হাসির ফলে সৃষ্ট সম্ভাব্য মানসিক ক্লান্তি, শিল্প ও সাহিত্যের প্লেটোর সমালোচনা এবং মিডিয়াতে মানব জীবনের চিত্রায়ন অন্বেষণ করে।",
      "এটি লেখকদের দায়িত্ব, কৌতুক এবং ব্যক্তিগত লড়াইয়ের মধ্যে যোগসূত্র এবং মোকাবেলা করার ব্যবস্থা হিসাবে হাস্যরসের ব্যবহারও পরীক্ষা করে।"
    ],
    "points": 122,
    "commentCount": 81,
    "retryCount": 0,
    "time": 1707568340
  }
]
