[
  {
    "id": 39001755,
    "title": "মাস্টারিং প্রোগ্রামিং: সময়, অনুশীলন এবং হ্যান্ডস-অন শেখার গুরুত্ব",
    "originLink": "https://norvig.com/21-days.html",
    "originBody": "",
    "commentLink": "https://news.ycombinator.com/item?id=39001755",
    "commentBody": "",
    "originSummary": [
      "নিবন্ধটি এমন বইয়ের সমালোচনা করে যা দ্রুত প্রোগ্রামিং শেখানোর প্রতিশ্রুতি দেয় এবং বিশেষজ্ঞ হওয়ার জন্য বছরের পর বছর অনুশীলনের প্রয়োজনীয়তা তুলে ধরে।",
      "এটি এই বইগুলির সীমাবদ্ধতার উপর জোর দেয় এবং নিজেকে চ্যালেঞ্জ করার এবং প্রতিক্রিয়া গ্রহণের তাৎপর্যের উপর জোর দেয়।",
      "সারসংক্ষেপটি হাতে-কলমে শেখার গুরুত্বকে তুলে ধরে এবং দক্ষতা অর্জনের জন্য ম্যালকম গ্ল্যাডওয়েলের 10,000 ঘন্টা অনুশীলনের ধারণাটি উল্লেখ করে। প্রোগ্রামিং আয়ত্ত করার জন্য প্রকৃত আগ্রহ এবং উত্সর্গ অপরিহার্য।"
    ],
    "commentSummary": [
      "ক্যারিয়ারে প্রোগ্রামিং বইয়ের প্রভাব এবং টেকনিক্যাল বইয়ের মাধ্যমে শেখার নস্টালজিয়াসহ প্রোগ্রামিং সম্পর্কিত বিভিন্ন বিষয় নিয়ে আলোচনা হয় এই আলোচনায়।",
      "চ্যাটজিপিটির মতো এআই সরঞ্জামগুলির ব্যবহার এবং প্রোগ্রামিং ভাষা শেখার চ্যালেঞ্জগুলিও আলোচনা করা হয়েছে।",
      "আলোচনায় দক্ষ প্রোগ্রামার হওয়ার জন্য ক্রমাগত শেখা, অনুশীলন, পরীক্ষা-নিরীক্ষা এবং চলমান উন্নতির গুরুত্বের উপর জোর দেওয়া হয়েছে।"
    ],
    "points": 497,
    "commentCount": 262,
    "retryCount": 0,
    "time": 1705331167
  },
  {
    "id": 39002138,
    "title": "এফএসআরএস: বর্ধিত মেমরি ধরে রাখার জন্য একটি পরবর্তী-প্রজন্মের স্পেসড পুনরাবৃত্তি অ্যালগরিদম",
    "originLink": "https://github.com/open-spaced-repetition/fsrs4anki/wiki/ABC-of-FSRS",
    "originBody": "",
    "commentLink": "https://news.ycombinator.com/item?id=39002138",
    "commentBody": "",
    "originSummary": [
      "এফএসআরএস হ'ল একটি আধুনিক স্পেসড পুনরাবৃত্তি অ্যালগরিদম যা আনকির ডিফল্ট অ্যালগরিদমের তুলনায় মেমরি ধরে রাখা এবং পর্যালোচনা সময়সূচী বাড়ায়।",
      "এটি \"মেমরির থ্রি কম্পোনেন্ট মডেল\" ব্যবহার করে এবং ব্যবহারকারীর পর্যালোচনা ইতিহাস বিশ্লেষণ করে সফলভাবে একটি কার্ড পুনরায় স্মরণ করার সম্ভাবনার উপর ভিত্তি করে সর্বোত্তম পর্যালোচনা বিরতি গণনা করে।",
      "এফএসআরএস ব্যবহারকারীদের তাদের পছন্দসই ধরে রাখার স্তর নির্বাচন করতে দেয়, আনকির ডিফল্ট অ্যালগরিদমের চেয়ে কম পর্যালোচনা প্রয়োজন এবং বিলম্বিত পর্যালোচনাগুলির সাথে কার্যকরভাবে কাজ করে। এটি এফএসআরএস 4 আঙ্কি হেলপার অ্যাড-অনের মাধ্যমে অতিরিক্ত বৈশিষ্ট্যও সরবরাহ করে।"
    ],
    "commentSummary": [
      "অংশগ্রহণকারীরা ভাষা এবং সংগীতের মতো বিভিন্ন বিষয় শেখার জন্য স্পেসড পুনরাবৃত্তি অ্যালগরিদম, বিশেষত আঙ্কি অ্যাপ্লিকেশন ব্যবহার সম্পর্কে একটি আলোচনায় জড়িত।",
      "কার্যকর ফ্ল্যাশকার্ড তৈরি এবং ধরে রাখার উন্নতি সম্পর্কিত কৌশল, অভিজ্ঞতা এবং মতামত ভাগ করা হয়।",
      "এফএসআরএস এবং সুপারমেমোর মতো বিভিন্ন অ্যালগরিদমের কার্যকারিতা অন্বেষণ করা হয়, কিছু অংশগ্রহণকারীরা প্রসঙ্গ এবং বিভিন্ন এক্সপোজারের উপর জোর দেয়, অন্যরা সর্বোত্তম ধরে রাখার জন্য কার্ড ফর্ম্যাটিং এবং সরলীকরণের দিকে মনোনিবেশ করে।"
    ],
    "points": 330,
    "commentCount": 93,
    "retryCount": 0,
    "time": 1705333203
  },
  {
    "id": 39003469,
    "title": "$ 50 এর নীচে উচ্চ গতির 11 জিবিপিএস ইউএসবি 4 নেটওয়ার্ক তৈরি করা",
    "originLink": "https://fangpenlin.com/posts/2024/01/14/high-speed-usb4-mesh-network/",
    "originBody": "",
    "commentLink": "https://news.ycombinator.com/item?id=39003469",
    "commentBody": "",
    "originSummary": [
      "লেখক, একজন সফটওয়্যার প্রকৌশলী, বিশ্বাস করেন যে সফ্টওয়্যার ছাড়াও হার্ডওয়্যার সম্পর্কে জ্ঞান থাকা অত্যন্ত গুরুত্বপূর্ণ।",
      "তারা খরচ কমাতে এডাব্লুএস ক্লাউড থেকে খালি ধাতব সার্ভারগুলিতে কিছু পরিষেবা স্থানান্তর িত করেছিল।",
      "লেখক একটি ইউএসবি 4 ইথারনেট ব্রিজ ব্যবহার করে একটি খালি ধাতব কুবারনেটস ক্লাস্টার তৈরি করেছেন, $ 47.98 মার্কিন ডলার ব্যয়ে 11 জিবিপিএস নেটওয়ার্ক গতি অর্জন করেছেন।",
      "তারা মিনি পিসির সুবিধাগুলি তুলে ধরে অবসরপ্রাপ্ত 1 ইউ সার্ভারবনাম মিনি পিসির ব্যয় এবং বিদ্যুৎ খরচ তুলনা করে।",
      "নেটওয়ার্ক কনফিগারেশনের জন্য নিক্সওএস ব্যবহার করা হয়েছিল এবং বেঞ্চমার্ক ফলাফল সরবরাহ করা হয়েছিল।",
      "লেখক ভবিষ্যতে উচ্চ গতির ইউএসবি / থান্ডারবোল্ট-ভিত্তিক নেটওয়ার্কগুলির সম্ভাবনা সম্পর্কে অনুমান করেছেন।"
    ],
    "commentSummary": [
      "আলোচনাটি ইউএসবি, ফায়ারওয়্যার, থান্ডারবোল্ট, ইথারনেট এবং এনভিএমই ড্রাইভ সহ বিভিন্ন নেটওয়ার্কিং বিকল্পগুলি অন্বেষণ করে।",
      "অংশগ্রহণকারীরা তাদের অভিজ্ঞতা এবং পছন্দগুলি ভাগ করে নেয়, গতি, ব্যয়, বিদ্যুৎ খরচ এবং সামঞ্জস্যতার মতো বিষয়গুলি নিয়ে আলোচনা করে।",
      "কথোপকথনএকটি নেটওয়ার্কিং সমাধান নির্বাচন করার সময় পৃথক প্রয়োজন এবং সংস্থান বিবেচনা করার গুরুত্বের উপর জোর দেয়।"
    ],
    "points": 327,
    "commentCount": 209,
    "retryCount": 0,
    "time": 1705339605
  },
  {
    "id": 39004963,
    "title": "SQLite 3.45: উন্নত কর্মক্ষমতা এবং ব্যবহারযোগ্যতার জন্য বর্ধিতকরণ এবং বাগ ফিক্স",
    "originLink": "https://www.sqlite.org/changes.html#version_3_45_0",
    "originBody": "",
    "commentLink": "https://news.ycombinator.com/item?id=39004963",
    "commentBody": "",
    "originSummary": [
      "সারসংক্ষেপটি এসকিউলাইট ডাটাবেস ম্যানেজমেন্ট সিস্টেমে আপডেট, বাগ ফিক্স এবং বর্ধিতকরণগুলি কভার করে।",
      "এসকিউএল এবং জেএসওএন ফাংশন, কোয়েরি প্ল্যানিং, কমান্ড-লাইন ইন্টারফেস এবং ত্রুটি পরিচালনায় উন্নতি করা হয়েছিল।",
      "আপডেটগুলি মেমরি লিক, বাগ ফিক্স এবং অপ্টিমাইজেশানের মতো সমস্যাগুলিও সমাধান করে।",
      "নতুন বৈশিষ্ট্যগুলির মধ্যে রয়েছে নতুন সিনট্যাক্সের জন্য সমর্থন, অন্যান্য ডাটাবেসের সাথে সামঞ্জস্যতা এবং নতুন কমান্ড যুক্ত করা।",
      "আপডেটগুলি এসকিউলাইটের কর্মক্ষমতা, সুরক্ষা এবং ব্যবহারযোগ্যতা উন্নত করার দিকে মনোনিবেশ করে।"
    ],
    "commentSummary": [
      "এসকিউলাইট 3.45 প্রকাশিত হয়েছে, যা জেএসওএন-নিবিড় অপারেশনগুলির জন্য উন্নত কর্মক্ষমতা এবং হ্রাস ডাটাবেস আকার সরবরাহ করে।",
      "নোশন ল্যাবস তাদের নেটিভ অ্যাপ্লিকেশনগুলিতে এসকিউলাইট ব্যবহার এবং ব্রাউজার এবং সার্ভার-সাইডে এর ব্যবহার অন্বেষণ করার কথা বিবেচনা করছে।",
      "আলোচনায় ওয়ান-ডিবি-পার-ভাড়াটিয়া, সম্ভাব্য সমাধান হিসাবে তুরসো, এসকিউলাইট বাইনারি, ইন্টারেক্টিভ রিলিজ নোট, কম্পাইলার সতর্কতা ঠিক করা এবং পোস্টগ্রেস বনাম এসকিউলাইট তুলনা অন্তর্ভুক্ত রয়েছে।"
    ],
    "points": 283,
    "commentCount": 50,
    "retryCount": 0,
    "time": 1705346684
  },
  {
    "id": 39007756,
    "title": "ব্লুস্কি ব্যবহারকারী আবিষ্কারের জন্য আরএসএস ফিড চালু করেছে",
    "originLink": "https://openrss.org/blog/bluesky-has-launched-rss-feeds",
    "originBody": "",
    "commentLink": "https://news.ycombinator.com/item?id=39007756",
    "commentBody": "",
    "originSummary": [
      "ব্লুস্কি আরএসএস ফিড চালু করেছে, ব্যবহারকারীদের যে কোনও ব্লুস্কি ব্যবহারকারীর জন্য একটি আরএসএস ফিড অ্যাক্সেস করতে সক্ষম করে, আরএসএস রিডার এবং ব্রাউজার এক্সটেনশনগুলির মাধ্যমে ব্যবহারকারী ফিড আবিষ্কারের সুবিধা দেয়।",
      "আরএসএস ফিডগুলিতে কেবল মাত্র পাবলিক পোস্ট অন্তর্ভুক্ত থাকে এবং লিঙ্কগুলি অন্তর্ভুক্ত থাকে না। ব্যবহারকারীরা আরএসএস ফিডগুলি উন্নত করতে ব্লুস্কিকে প্রতিক্রিয়া দিতে পারেন।",
      "ওপেন আরএসএস, যা স্বেচ্ছাসেবী অনুদানের উপর নির্ভর করে, ব্লুস্কি আরএসএস ফিডগুলির তাদের সংস্করণও সরবরাহ করে।"
    ],
    "commentSummary": [
      "আলোচনাটি ব্লুস্কিকে কেন্দ্র করে, টুইটারের সম্ভাব্য প্রতিস্থাপন, এবং পক্ষপাতদুষ্ট সামগ্রীর সুপারিশ, এআই ফিল্টারগুলির প্রয়োজনীয়তা এবং ডেটা সুরক্ষা উদ্বেগের মতো বিভিন্ন বিষয় কভার করে।",
      "ব্যবহারকারীরা ব্লুস্কির অনন্য বৈশিষ্ট্য, আর্থিক স্থায়িত্ব, সীমিত ব্যবহারকারীর ব্যস্ততা এবং স্ব-প্রমাণীকরণ পোস্টগুলিও অন্বেষণ করে।",
      "অন্যান্য আলোচনায় ব্লুস্কির আমন্ত্রণ ব্যবস্থা, প্ল্যাটফর্মে বিষাক্ততা, অন্যান্য সামাজিক মিডিয়া প্ল্যাটফর্মের সাথে তুলনা এবং ব্যবহারকারীদের অভিজ্ঞতা এবং মতামত স্পর্শ করা হয়েছে। জ্যাক ডরসির সম্পৃক্ততা, আরএসএস ফিডের ভবিষ্যত এবং ম্যাস্টোডনের উপকারিতা এবং অসুবিধাগুলিও উল্লেখ করা হয়েছে। প্রতিযোগিতার মধ্যে ব্লুস্কির ভবিষ্যত সাফল্য অনিশ্চিত।"
    ],
    "points": 262,
    "commentCount": 120,
    "retryCount": 0,
    "time": 1705363540
  },
  {
    "id": 39003417,
    "title": "ওনিগিরির উত্থান: জাপানের আরামদায়ক খাদ্য বিপ্লব",
    "originLink": "https://one-from-nippon.ghost.io/onigiri/",
    "originBody": "",
    "commentLink": "https://news.ycombinator.com/item?id=39003417",
    "commentBody": "",
    "originSummary": [
      "ওনিগিরি একটি ঐতিহ্যবাহী জাপানি খাবার যা বিভিন্ন উপাদানে ভরা একটি চালের বল এবং নোরি (সামুদ্রিক শৈবাল) এ মোড়ানো হয়।",
      "এটি যুদ্ধোত্তর জাপানে সুপারমার্কেট এবং সুবিধাজনক দোকানে বিক্রি হওয়া একটি সুবিধাজনক এবং পরিচিত খাদ্য আইটেম হিসাবে জনপ্রিয় হয়ে ওঠে।",
      "ওনিগিরি জাপানের সুবিধাজনক দোকানগুলির গল্পের সাথে ঘনিষ্ঠভাবে জড়িত, বিভিন্ন চেইনগুলি সতেজতা, স্বাদ, বৈচিত্র্য এবং প্যাকেজিংয়ের উপর প্রতিযোগিতা করে।"
    ],
    "commentSummary": [
      "নিবন্ধটি জাপানের কানসাই এবং কানতু অঞ্চলের মধ্যে চলমান প্রতিদ্বন্দ্বিতা অন্বেষণ করে, ভাষা, জনসংখ্যা এবং অভিবাসনের মতো কারণগুলি পরীক্ষা করে যা এই প্রতিদ্বন্দ্বিতায় অবদান রাখে।",
      "এটি পুরো শস্য চালের ক্রমবর্ধমান জনপ্রিয়তা, সুবিধাজনক স্টোর ওনিগিরিতে টুনা গুণমান হ্রাস এবং নিরামিষাশী বিকল্পগুলির প্রাপ্যতা সহ ওনিগিরির প্রবণতাগুলি নিয়ে আলোচনা করে।",
      "নিবন্ধটি বিভিন্ন দেশে পাওয়া ওনিগিরির বিভিন্ন বৈচিত্র এবং প্যাকেজিং খোলার চ্যালেঞ্জগুলিও তুলে ধরেছে।"
    ],
    "points": 256,
    "commentCount": 108,
    "retryCount": 0,
    "time": 1705339347
  },
  {
    "id": 39002740,
    "title": "সফ্টওয়্যার ডেভেলপমেন্ট পুনরায় কল্পনা করা: স্ক্রামকে সমালোচনা করা এবং ব্যক্তিগতকৃত টিমওয়ার্ক প্রচার করা",
    "originLink": "https://blog.mb-consulting.dev/scrum-sucks-9960011fc5cf",
    "originBody": "",
    "commentLink": "https://news.ycombinator.com/item?id=39002740",
    "commentBody": "",
    "originSummary": [
      "নিবন্ধটি সফ্টওয়্যার বিকাশে স্ক্রামের বাস্তবায়নের সমালোচনা করে, পরামর্শ দেয় যে দলগুলির পরিবর্তে তাদের নিজস্ব পদ্ধতি সংজ্ঞায়িত করা উচিত।",
      "এটি স্ক্রামের চ্যালেঞ্জ এবং জটিলতাগুলি তুলে ধরেছে, যেমন মেট্রিক্সের অপব্যবহার এবং দলগুলির মধ্যে বিশ্বাসের প্রয়োজনীয়তা।",
      "লেখক প্রকল্প পরিচালনায় সহযোগিতা, ক্রমাগত উন্নতি এবং স্টেকহোল্ডারদের সম্পৃক্ততা, প্রকৌশল পরিষেবা এবং কোচিং প্রদানের উপর জোর দিয়েছেন।"
    ],
    "commentSummary": [
      "কথোপকথনটি বিভিন্ন কাজের পরিবেশে চটজলদি পদ্ধতি, বিশেষত স্ক্রাম ব্যবহারের উপর দৃষ্টি নিবদ্ধ করে।",
      "অংশগ্রহণকারীরা অত্যধিক সভা, দুর্বল যোগাযোগ এবং বিশ্বাসের অভাবের মতো চ্যালেঞ্জগুলি নিয়ে আলোচনা করে।",
      "কানবান এবং শেপআপের মতো বিকল্প পদ্ধতির কথা উল্লেখ করা হয়েছে, যা চটপটে পদ্ধতির কার্যকারিতা নিয়ে বিতর্ক ের জন্ম দিয়েছে।"
    ],
    "points": 218,
    "commentCount": 273,
    "retryCount": 0,
    "time": 1705336698
  },
  {
    "id": 39003292,
    "title": "এইচটিএমএক্স জিরো-ক্লজ বিএসডি লাইসেন্সে স্যুইচ করে, সীমাহীন ব্যবহার সক্ষম করে",
    "originLink": "https://github.com/bigskysoftware/htmx/commit/e16f1865a494b6281f8a44ed0db5338e718b3f07",
    "originBody": "",
    "commentLink": "https://news.ycombinator.com/item?id=39003292",
    "commentBody": "",
    "originSummary": [
      "রিপোজিটরি \"বিগস্কাইসফটওয়্যার / এইচটিএমএক্স\" তার লাইসেন্সটি বিএসডি 2-ক্লজ লাইসেন্স থেকে 0-ক্লজ বিএসডি লাইসেন্সে পরিবর্তন করেছে।",
      "এই পরিবর্তনটি কোনও ফি ছাড়াই সফ্টওয়্যারটির সীমাহীন ব্যবহার, অনুলিপি, পরিবর্তন এবং বিতরণের অনুমতি দেয়।",
      "ব্যবহারকারীরা নতুন লাইসেন্সের জন্য ইতিবাচক প্রতিক্রিয়া এবং কৃতজ্ঞতা প্রকাশ করছেন।"
    ],
    "commentSummary": [
      "এইচটিএমএক্স সফ্টওয়্যার লাইব্রেরি তার লাইসেন্সটি জিরো-ক্লজ বিএসডিতে পরিবর্তন করেছে, এটি একটি অনুমোদিত ওপেন-সোর্স লাইসেন্স।",
      "এইচটিএমএক্স-এ মাইক্রোসফটের কথিত আগ্রহ নিয়ে সোশ্যাল মিডিয়ায় কৌতুক হয়েছিল।",
      "অনুচ্ছেদটি সফ্টওয়্যার প্রকল্পগুলির বিশ্বাসযোগ্যতা এবং পেশাদারিত্ব ের উপর আলোচনা এবং ডাটাবেস ম্যানেজমেন্ট সিস্টেম হিসাবে মঙ্গোডিবির বিশ্বস্ততা সম্পর্কে উদ্বেগগুলি অন্বেষণ করে। এটি টুইটারে হাস্যরস এবং পেশাদারিত্ব, ওপেন-সোর্স লাইসেন্স এবং তাদের সীমাবদ্ধতা, বাতিল সংস্কৃতি, ফেসবুক, ভ্যাক্সার বিরোধী এবং রাজনৈতিক বক্তৃতা সম্পর্কে কথোপকথনকেও স্পর্শ করে।"
    ],
    "points": 199,
    "commentCount": 109,
    "retryCount": 0,
    "time": 1705338867
  },
  {
    "id": 39008533,
    "title": "ভিমকে একটি মোডলেস এডিটরে রূপান্তর করুন, স্ট্যান্ডার্ড কী বাইন্ডিং এবং উন্নত ব্যবহারকারী-বন্ধুত্ব সহ",
    "originLink": "https://github.com/SebastianMuskalla/ModelessVim",
    "originBody": "",
    "commentLink": "https://news.ycombinator.com/item?id=39008533",
    "commentBody": "",
    "originSummary": [
      "রিপোজিটরি ভিমকে একটি মোডলেস এডিটরে রূপান্তর করতে কনফিগ ফাইল সরবরাহ করে, যা গ্রাফিকাল সম্পাদকদের সাথে পরিচিত ব্যবহারকারীদের নেভিগেট করা সহজ করে তোলে।",
      "এটিতে স্ট্যান্ডার্ড কী বাইন্ডিং, একটি শীর্ষ ইনফোবার, একটি নীচের স্ট্যাটাসবার এবং ডিফল্ট সেটিংসের বিকল্প রয়েছে।",
      "কনফিগারেশনটি ভিমের নির্দিষ্ট প্ল্যাটফর্ম এবং সংস্করণগুলিতে পরীক্ষা করা হয়েছে এবং এমআইটি লাইসেন্সের অধীনে বিতরণ করা হয়েছে।"
    ],
    "commentSummary": [
      "আলোচনাটি মূলত পাঠ্য সম্পাদকদের ঘিরে আবর্তিত হয়, ভিম এবং এর বৈশিষ্ট্যগুলির উপর দৃষ্টি নিবদ্ধ করে।",
      "ব্যবহারকারীরা ইতিবাচক অভিজ্ঞতা ভাগ করে নেয় এবং হেলিক্স সম্পাদক নিয়ে আলোচনা করে, এর সহায়ক বৈশিষ্ট্যগুলি তুলে ধরে।",
      "কথোপকথনটি কুমড়োর পাইতে টিনজাত এবং বাড়িতে তৈরি কুমড়োর পিউরির ব্যবহারের পাশাপাশি কুমড়োর সংজ্ঞা এবং বিভিন্ন ধরণের স্কোয়াশের ব্যবহারের তুলনা এবং বিতর্ক করে।",
      "পরে, আলোচনাটি ভিম, ইম্যাকস এবং ভিএসকোডের মধ্যে পার্থক্যগুলি অনুসন্ধান করে, ব্যবহারকারী-বন্ধুত্ব, কীবাইন্ডিং এবং সীমাবদ্ধতাগুলি স্পর্শ করে।",
      "সামগ্রিক কথোপকথন বিভিন্ন পাঠ্য সম্পাদকদের কার্যকারিতা এবং কার্যকারিতা সম্পর্কে ব্যক্তিগত পছন্দ এবং বিভিন্ন মতামত প্রতিফলিত করে।"
    ],
    "points": 183,
    "commentCount": 168,
    "retryCount": 0,
    "time": 1705370732
  },
  {
    "id": 39002643,
    "title": "ফসিফাই: সহজ মোবাইল সরঞ্জামগুলির জন্য কমিউনিটি-সমর্থিত ওপেন-সোর্স বিকল্প",
    "originLink": "https://github.com/FossifyOrg",
    "originBody": "",
    "commentLink": "https://news.ycombinator.com/item?id=39002643",
    "commentBody": "",
    "originSummary": [
      "ফসিফাই একটি ওপেন সোর্স মোবাইল অ্যাপ্লিকেশন প্ল্যাটফর্ম যা বন্ধ @SimpleMobileTools কাজ চালিয়ে যাওয়ার লক্ষ্য রাখে।",
      "এটি সম্প্রদায়-সমর্থিত এবং বিজ্ঞাপন-মুক্ত, এবং ব্যবহারকারীদের অবদানকে উত্সাহিত করে।",
      "তারা গিটহাব স্পন্সর, প্যাট্রিয়ন, PayPal, লিবারপে এবং ক্রিপ্টোকারেন্সি অনুদান সহ একাধিক সমর্থন বিকল্প সরবরাহ করে এবং সম্প্রদায়ের সমর্থনকে মূল্য দেয়।"
    ],
    "commentSummary": [
      "সিম্পল মোবাইল টুলস অ্যাপ্লিকেশনটি একটি অ্যাডওয়্যার সংস্থা দ্বারা অধিগ্রহণ করা হয়েছিল, যা ফসিফাইঅর্গ প্রকল্প দ্বারা একটি ফোর্ক বিকাশকে উত্সাহিত করেছিল।",
      "ফসিফাই প্রকল্পের লক্ষ্য এফ-ড্রয়েডে অ্যাপ্লিকেশনগুলির পরিবর্তিত সংস্করণগুলি প্রকাশ করা, ফসিফাই গ্যালারি অ্যাপ্লিকেশনটি ইতিমধ্যে উপলব্ধ।",
      "ব্যবহারকারীরা অ্যাপ্লিকেশনগুলির ওপেন-সোর্স এবং অ-গুপ্তচরবৃত্তির প্রকৃতির প্রশংসা করেন, তবে লাইসেন্সিং সমস্যা এবং বাহ্যিক অবদানের ভাগ্য সম্পর্কে উদ্বেগ রয়েছে।"
    ],
    "points": 177,
    "commentCount": 40,
    "retryCount": 0,
    "time": 1705336193
  },
  {
    "id": 39009779,
    "title": "এআই নিরাপত্তা সংস্থাগুলি ওপেন-সোর্স এআই-এর সীমাবদ্ধতার জন্য চাপ দিচ্ছে, বিতর্ক ের জন্ম দিয়েছে",
    "originLink": "https://1a3orn.com/sub/machine-learning-bans.html",
    "originBody": "",
    "commentLink": "https://news.ycombinator.com/item?id=39009779",
    "commentBody": "",
    "originSummary": [
      "এআই সুরক্ষা সংস্থাগুলি কম্পিউটেশনাল রিসোর্স, প্যারামিটার গণনা বা বেঞ্চমার্ক পারফরম্যান্সের মতো নির্দিষ্ট মানদণ্ডের উপর ভিত্তি করে ওপেন-সোর্স এআই মডেলগুলি নিষিদ্ধ বা সীমাবদ্ধ করার আহ্বান জানাচ্ছে।",
      "এই প্রস্তাবিত নিষেধাজ্ঞাগুলির লক্ষ্য এআই সুরক্ষা বাড়ানো, তবে সমালোচকরা যুক্তি দেখান যে এগুলি এই ক্ষেত্রে গবেষণা এবং উন্নয়নকে বাধা গ্রস্ত করবে।",
      "ওপেন-সোর্স এআই আন্দোলনকে সমন্বয় উন্নত করতে হবে এবং ওপেন-সোর্স এআই-এর ভবিষ্যত রক্ষার জন্য এই ওপেন-সোর্স-বিরোধী উদ্যোগগুলি মোকাবেলা করতে হবে।"
    ],
    "commentSummary": [
      "অনুচ্ছেদটি কৃত্রিম বুদ্ধিমত্তা (এআই) এর বিকাশ এবং নিয়ন্ত্রণ এবং এর চারপাশের বিভিন্ন উদ্বেগকে অন্তর্ভুক্ত করে।",
      "ওপেন-সোর্স এআই-এর অপরাধীকরণ, একটি নির্দিষ্ট সক্ষমতা স্তর ছাড়িয়ে এআই নিষিদ্ধ করা এবং এআই সুরক্ষা ঝুঁকির জন্য প্রমাণের বোঝা নিয়ে বিতর্ক রয়েছে।",
      "আলোচনাটি এআই-এর ঝুঁকি এবং সুবিধাগুলি, সুপারইন্টেলিজেন্স মডেলিংয়ের চ্যালেঞ্জগুলি, রাজনৈতিক প্রক্রিয়াগুলির সম্ভাব্য ম্যানিপুলেশন এবং এজিআই-এর অনিশ্চিত অস্তিত্বঅনুসন্ধান করে।"
    ],
    "points": 176,
    "commentCount": 115,
    "retryCount": 0,
    "time": 1705382258
  },
  {
    "id": 38999517,
    "title": "বিশ্বের সবচেয়ে ধনীরা তাদের সম্পদদ্বিগুণ করে দরিদ্রতম: অক্সফামের প্রতিবেদন",
    "originLink": "https://www.theguardian.com/inequality/2024/jan/15/worlds-five-richest-men-double-their-money-as-poorest-get-poorer",
    "originBody": "",
    "commentLink": "https://news.ycombinator.com/item?id=38999517",
    "commentBody": "",
    "originSummary": [
      "২০২০ সাল থেকে বিশ্বের শীর্ষ পাঁচ বিলিয়নিয়ারের সম্পদ দ্বিগুণেরও বেশি বেড়েছে, অন্যদিকে বিশ্বের দরিদ্রতম ৬০ শতাংশ মানুষ অর্থ হারিয়েছেন।",
      "অক্সফামের প্রতিবেদনে সম্পদের ব্যবধান বাড়ার বিষয়টি তুলে ধরা হয়েছে এবং আগামী দশকে ট্রিলিয়নিয়ারের সম্ভাব্য উত্থানের পূর্বাভাস দেওয়া হয়েছে।",
      "শীর্ষ পাঁচ বিলিয়নিয়ারের সম্মিলিত সম্পদ বেড়েছে ৪৬৪ বিলিয়ন ডলার, আর দরিদ্রতম ৪.৭৭ বিলিয়ন মানুষের মোট সম্পদ কমেছে ০.২%।",
      "অক্সফাম সম্পদের ভারসাম্যহীনতা নিরসনের সমাধান হিসাবে ১০ মিলিয়ন পাউন্ডের বেশি সম্পদের উপর ১% থেকে ২% সম্পদ কর প্রস্তাব করেছে, যা যুক্তরাজ্যের জন্য প্রতি বছর ২২ বিলিয়ন পাউন্ড সংগ্রহ করতে পারে।"
    ],
    "commentSummary": [
      "এই আলোচনায় সম্পদ বৈষম্যের একাধিক মাত্রা অন্তর্ভুক্ত রয়েছে, যার মধ্যে দরিদ্রদের মুখোমুখি হওয়া চ্যালেঞ্জ এবং সমস্ত ব্যক্তির জন্য মৌলিক প্রয়োজনীয়তা সরবরাহ ের বিষয়ে চলমান বিতর্ক রয়েছে।",
      "কথোপকথনটি পুঁজিবাদ এবং ধনী অভিজাতদের সমালোচনা করে, বিভিন্ন অর্থনৈতিক মতাদর্শ এবং সম্পদ সংগ্রহে ভাগ্য এবং সরকারের হস্তক্ষেপের ভূমিকা অন্বেষণ করে।",
      "অর্থনীতিতে অটোমেশনের প্রভাব এবং \"মূলধন থেকে পালানোর\" ধারণার পাশাপাশি চরম সম্পদ সংগ্রহের পরিণতি, অতি-ধনীদের প্রভাব এবং সম্পদ করগুলির মতো সম্ভাব্য সমাধানগুলিও আলোচনা করা হয়।"
    ],
    "points": 172,
    "commentCount": 329,
    "retryCount": 0,
    "time": 1705316988
  },
  {
    "id": 39010070,
    "title": "সফটওয়্যার গ্লিচ বিপর্যয়: পোস্ট অফিস কেলেঙ্কারিতে জীবন ধ্বংস",
    "originLink": "https://www.cnn.com/2024/01/13/business/uk-post-office-fujitsu-horizon-scandal/index.html",
    "originBody": "",
    "commentLink": "https://news.ycombinator.com/item?id=39010070",
    "commentBody": "",
    "originSummary": [
      "প্রদত্ত তথ্যের মধ্যে কোড স্নিপেট এবং তাদের কার্যকারিতার বিবরণ অন্তর্ভুক্ত রয়েছে, যেমন সিএসএস স্টাইলিং, জাভাস্ক্রিপ্ট কার্যকারিতা, বিজ্ঞাপন কনফিগারেশন, ব্যবহারকারীর সম্মতি পরিচালনা এবং ডেটা এনকোডিং।",
      "ইউকে পোস্ট অফিস কেলেঙ্কারি নিয়ে আলোচনা করা হয়, একটি সফ্টওয়্যার ত্রুটি জড়িত যা সাব-পোস্টমাস্টারদের জন্য আর্থিক অসঙ্গতি সৃষ্টি করে, যার ফলে গুরুতর পরিণতি, আইনি লড়াই এবং প্রাণহানি ঘটে।"
    ],
    "commentSummary": [
      "এই নিবন্ধটি সফ্টওয়্যার ত্রুটির বাস্তব জীবনের ঘটনাগুলি নিয়ে আলোচনা করে, কারাগার, দেউলিয়া হওয়া এবং এমনকি আত্মহত্যা সহ তাদের মারাত্মক পরিণতিগুলি তুলে ধরে।",
      "এটি সফ্টওয়্যার প্রকৌশলে জবাবদিহিতা এবং সুরক্ষার প্রয়োজনীয়তার উপর জোর দেয়, পাশাপাশি সফ্টওয়্যার ত্রুটিগুলির প্রভাবকে হ্রাস করে।",
      "নিবন্ধটি সফ্টওয়্যার সমস্যাগুলিকে বড় সমস্যা হওয়া থেকে রোধ করার জন্য প্রাথমিকভাবে সমাধানের গুরুত্বের উপর জোর দেয় এবং অ-প্রযুক্তিগত ব্যক্তিদের সফ্টওয়্যার গুণমানকে গুরুত্বসহকারে নেওয়ার চ্যালেঞ্জগুলি তুলে ধরে।"
    ],
    "points": 168,
    "commentCount": 132,
    "retryCount": 0,
    "time": 1705386155
  }
]
