[
  {
    "id": 38992601,
    "title": "Vanna.ai: চ্যাট ইন্টারফেসের মাধ্যমে SQL প্রশ্ন তৈরি করা",
    "originLink": "https://github.com/vanna-ai/vanna",
    "originBody": "",
    "commentLink": "https://news.ycombinator.com/item?id=38992601",
    "commentBody": "",
    "originSummary": [
      "ভান্না একটি ওপেন সোর্স পাইথন ফ্রেমওয়ার্ক যা প্রশিক্ষিত মডেলগুলির উপর ভিত্তি করে এসকিউএল প্রশ্ন তৈরি করে, ব্যবহারকারীদের প্রশ্ন জিজ্ঞাসা করতে এবং ফলাফল হিসাবে এসকিউএল প্রশ্নগুলি গ্রহণ করতে দেয়।",
      "ফ্রেমওয়ার্কটি জুপিটার নোটবুক, স্ট্রিমলাইট, ফ্লাস্ক এবং স্ল্যাকের মতো ব্যবহারকারী ইন্টারফেস সরবরাহ করে।",
      "ভান্না পিপ ব্যবহার করে ইনস্টল করা যেতে পারে এবং ডিডিএল বিবৃতি, ডকুমেন্টেশন বা এসকিউএল কোয়েরি ব্যবহার করে প্রশিক্ষণ দেওয়া যেতে পারে। এটি জটিল ডেটাসেটগুলিতে উচ্চ নির্ভুলতা সরবরাহ করে, যে কোনও এসকিউএল ডাটাবেস সমর্থন করে এবং স্ব-শেখার অনুমতি দেয়। ব্যবহারকারীরা তাদের নিজস্ব এলএলএম বা ভেক্টর ডাটাবেস ব্যবহার করতে ভ্যানাকে প্রসারিত করতে পারেন।"
    ],
    "commentSummary": [
      "আলোচনাটি এসকিউএল ডাটাবেসের সাথে ইন্টারঅ্যাক্ট করার জন্য বিভিন্ন এআই-চালিত সরঞ্জাম এবং প্রযুক্তিগুলি অন্বেষণ করে, যেমন Vanna.ai, Louie.ai এবং এই ক্ষেত্রে মাইক্রোসফ্টের সম্পৃক্ততা।",
      "এটি এসকিউএল মিথস্ক্রিয়ায় ভাষা মডেল এবং প্রাকৃতিক ভাষা প্রশ্নগুলির ব্যবহার, এআই-সহায়তাযুক্ত এসকিউএলের চ্যালেঞ্জ এবং সুবিধাগুলি নিয়ে আলোচনা করে।",
      "কথোপকথনটি স্কিমা ডিজাইন, বর্তমান মডেলগুলির সীমাবদ্ধতা এবং এসকিউএল প্রশ্ন গুলি লেখার জন্য এআই কো-পাইলটদের ভবিষ্যতের সম্ভাবনাকেও স্পর্শ করে, ডাটাবেস পরিচালনা এবং বিশ্লেষণের কাজগুলি সহজ করার জন্য এআই ব্যবহারের ক্রমবর্ধমান আগ্রহকে তুলে ধরে।"
    ],
    "points": 448,
    "commentCount": 192,
    "retryCount": 0,
    "time": 1705255086
  },
  {
    "id": 38994817,
    "title": "ওয়ার্ল্ড অফ ওয়ারক্রাফ্টের আরএনজি উন্মোচন: কীভাবে এক কিশোর গেমটিকে পরাজিত করার উপায় খুঁজে পেয়েছিল",
    "originLink": "https://orlp.net/blog/when-random-isnt/",
    "originBody": "",
    "commentLink": "https://news.ycombinator.com/item?id=38994817",
    "commentBody": "",
    "originSummary": [
      "লেখক ওয়ার্ল্ড অফ ওয়ারক্রাফ্ট খেলতে এবং লুয়া প্রোগ্রামিং ব্যবহার করে অ্যাড-অন তৈরি করতে তাদের কিশোর অভিজ্ঞতা ভাগ করেছেন।",
      "তারা গেমটিতে অটোমেশন রোধে ব্লিজার্ড গেমস দ্বারা বাস্তবায়িত নিরাপত্তা ব্যবস্থা নিয়ে আলোচনা করে।",
      "লেখক গেমের এলোমেলো নম্বর জেনারেটরকে ম্যানিপুলেট করে একটি ফাঁক আবিষ্কার করেছেন, যা স্বয়ংক্রিয় সিদ্ধান্ত গ্রহণের অনুমতি দেয়। যাইহোক, ব্লিজার্ড গেমস দ্বারা সম্ভাব্য সংশোধন বা অ্যালগরিদম পরিবর্তনের কারণে এই শোষণ এখনও কাজ করে কিনা তা স্পষ্ট নয়।"
    ],
    "commentSummary": [
      "অনলাইন ফোরাম আলোচনায় জাভা এবং এমএসভিসিতে এলোমেলো সংখ্যা জেনারেটরের মধ্যে তুলনা এবং ভ্যানিলা ওয়াওতে মারসেন টুইস্টার আরএনজি ব্যবহার সহ বিস্তৃত বিষয় অন্তর্ভুক্ত রয়েছে।",
      "কথোপকথনটি পুরানো ইন্টারনেট ফোরামের নস্টালজিয়া এবং অনলাইন ফোরামের কাঠামোকেও স্পর্শ করে।",
      "আলোচিত অন্যান্য বিষয়গুলির মধ্যে রয়েছে ভিডিও গেম অর্থনীতি, উচ্চ ফ্রিকোয়েন্সি ট্রেডিং এবং ডাব্লুওও নিলাম হাউসে অর্থ উপার্জনের কৌশল।"
    ],
    "points": 280,
    "commentCount": 86,
    "retryCount": 0,
    "time": 1705269389
  },
  {
    "id": 38990080,
    "title": "গাড়ির সাথে হতাশা: স্মার্ট টিভির তুলনায় অতিরিক্ত বৈশিষ্ট্য এবং দুর্বল নকশা পছন্দ",
    "originLink": "https://petargyurov.com/2024-01-14/cars-suck-man",
    "originBody": "",
    "commentLink": "https://news.ycombinator.com/item?id=38990080",
    "commentBody": "",
    "originSummary": [
      "লেখক স্মার্ট টিভিতে দেখা সমস্যাগুলির সাথে সামঞ্জস্য রেখে গাড়ির বর্তমান অবস্থার সাথে অসন্তুষ্টি তুলে ধরেছেন।",
      "অত্যধিক বৈশিষ্ট্য, দুর্বল নকশা পছন্দ এবং টাচস্ক্রিনের পিছনে লুকানো বোতাম এবং অত্যধিক উজ্জ্বল এলইডি লাইটের মতো ব্যবহারকারী-বান্ধব উপাদানগুলি সমালোচিত হয়।",
      "বৃহত্তর যানবাহনের প্রবণতা, সাবস্ক্রিপশন-স্টাইল পরিকল্পনা এবং গোপনীয়তা লঙ্ঘনের কথাও উল্লেখ করা হয়েছে, লেখকের পুরানো টয়োটা করোলার মতো আরও সহজ এবং আরও ব্যবহারকারী-বান্ধব গাড়ির আহ্বান জানানো হয়েছে।"
    ],
    "commentSummary": [
      "নিবন্ধ এবং আলোচনায় অতিরিক্ত প্রযুক্তি এবং প্রবিধানের সাথে অসন্তুষ্টি, মিনিমালিস্ট এবং ওপেন-সোর্স গাড়ির ডিজাইনের সুবিধা এবং এসইউভি এবং ক্রসওভারগুলির জনপ্রিয়তা সহ আধুনিক গাড়ি সম্পর্কিত বেশ কয়েকটি বিষয় স্পর্শ করা হয়েছে।",
      "মন্তব্যকারীরা গাড়ির সরলতা, কাস্টমাইজেশন এবং ব্যবহারিকতার পাশাপাশি ব্যয়, সুরক্ষা এবং পরিবেশগত প্রভাব সম্পর্কে উদ্বেগের জন্য তাদের পছন্দগুলি প্রকাশ করে।",
      "কথোপকথনটি সাশ্রয়ী মূল্যের, ব্যবহারকারী-বান্ধব এবং নির্ভরযোগ্য যানবাহনের প্রয়োজনীয়তার উপর জোর দেয় যা ভোক্তাদের আকাঙ্ক্ষা পূরণ করে।"
    ],
    "points": 185,
    "commentCount": 289,
    "retryCount": 0,
    "time": 1705237723
  },
  {
    "id": 38990755,
    "title": "আপনার ডিজিটাল গোপনীয়তা পুনরুদ্ধার: ডেটা ব্রোকারদের কাছ থেকে ডেটা মুছে ফেলা",
    "originLink": "https://www.cybercollective.org/blog/how-to-delete-your-data-from-data-brokers",
    "originBody": "",
    "commentLink": "https://news.ycombinator.com/item?id=38990755",
    "commentBody": "",
    "originSummary": [
      "ডেটা ব্রোকাররা আমাদের জ্ঞান বা সম্মতি ছাড়াই ব্যক্তিগত তথ্য সংগ্রহ এবং বিক্রি করে, আমাদের ডিজিটাল গোপনীয়তার সাথে আপস করে।",
      "ব্লগটি ডেটা ব্রোকারদের কাছ থেকে ডেটা অপসারণের অনুরোধ করে এবং সিসিপিএ এবং জিডিপিআরের মতো ভোক্তা সুরক্ষা আইন ব্যবহার করে কীভাবে ব্যক্তিরা তাদের ডেটার উপর নিয়ন্ত্রণ পুনরুদ্ধার করতে পারে সে সম্পর্কে পদক্ষেপ সরবরাহ করে।",
      "এটি অনলাইন সম্মতি সম্পর্কে সচেতন হওয়ার এবং ডেটা ব্রোকারদের দ্বারা ডেটা সংগ্রহের বিরুদ্ধে লড়াই করার জন্য সক্রিয়ভাবে একজনের ডিজিটাল পদচিহ্ন পরিচালনাকরার গুরুত্বের উপর জোর দেয়।"
    ],
    "commentSummary": [
      "আলোচনাটি ডেটা গোপনীয়তা এবং ডেটা ব্রোকার এবং অ্যাপ্লিকেশনগুলির দ্বারা ব্যক্তিগত তথ্যের সম্ভাব্য বিক্রয় সম্পর্কে উদ্বেগকে কেন্দ্র করে।",
      "ব্যবহারকারীরা ডাটাবেস থেকে ব্যক্তিগত ডেটা অপসারণের জন্য বিভিন্ন সরঞ্জাম এবং পরিষেবাগুলির পরামর্শ দেয়, অপ্ট-আউট পরিষেবাগুলির নির্ভরযোগ্যতা এবং ডেটা অপসারণ পরিষেবাগুলির কার্যকারিতা ঘিরে বিতর্কসহ।",
      "ডেটা ফাঁস কমাতে অনন্য এবং ডোমেন-নির্দিষ্ট ইমেল ঠিকানাগুলি ব্যবহার করার পরামর্শ দেওয়া হয়, আবার কেউ কেউ ব্যক্তিগত তথ্য সুরক্ষার জন্য এলএলসি স্থাপনের বিকল্পটি নিয়ে আলোচনা করে। কথোপকথনটি অনলাইনে ব্যক্তিগত ডেটা সুরক্ষিত করার তাৎপর্য এবং এর সাথে জড়িত বাধাগুলির উপর জোর দেয়।"
    ],
    "points": 181,
    "commentCount": 89,
    "retryCount": 0,
    "time": 1705242863
  },
  {
    "id": 38992292,
    "title": "ব্লুফিন প্রজেক্ট ডেভেলপার-ফোকাসড, ক্লাউড-নেটিভ লিনাক্স হিসাবে পুনরায় পরিচিত",
    "originLink": "https://www.ypsidanger.com/announcing-project-bluefin/",
    "originBody": "",
    "commentLink": "https://news.ycombinator.com/item?id=38992292",
    "commentBody": "",
    "originSummary": [
      "ব্লুফিন প্রকল্পটি projectbluefin.io হিসাবে পুনরায় চালু করা হয়েছে, একটি নির্ভরযোগ্য ডেস্কটপ অভিজ্ঞতার সাথে ফেডোরা সিলভারব্লুর একটি কাস্টম চিত্র সরবরাহ করে।",
      "ব্লুফিন কোনও বিতরণ নয় তবে ডিফল্ট চিত্রের শীর্ষে একটি পারমাণবিক স্তর, গিটহাবের মাধ্যমে বিতরণে অটোমেশন সরবরাহ করে এবং অবিশ্বস্ত লিনাক্স ডেস্কটপে অসন্তুষ্ট ব্যবহারকারীদের জন্য একটি বিকল্প।",
      "প্রকল্পটিতে ব্লুফিন-ডিএক্স নামে একটি বিকাশকারী চিত্র অন্তর্ভুক্ত রয়েছে, যা ডেভেলপারদের জন্য অতিরিক্ত সরঞ্জাম এবং নমনীয়তা সরবরাহ করে, ক্লাউড-নেটিভ প্রযুক্তি গ্রহণকে ত্বরান্বিত করার এবং ওপেন-সোর্স বাস্তুতন্ত্রের স্থায়িত্ব বাড়ানোর লক্ষ্যে।"
    ],
    "commentSummary": [
      "ব্লুফিন একটি ক্লাউড-নেটিভ লিনাক্স ডিস্ট্রিবিউশন যা ফেডোরা সিলভারব্লু ভিত্তিক, ডেভেলপারদের জন্য ডিজাইন করা হয়েছে।",
      "এতে একটি অপরিবর্তনীয় রুট ফাইল সিস্টেম, আপডেটের জন্য একটি কনটেইনার রেজিস্ট্রি এবং অতিরিক্ত হার্ডওয়্যার সমর্থন রয়েছে।",
      "ইউনিভার্সাল ব্লু একটি ক্লাউড-ভিত্তিক স্থাপনা প্ল্যাটফর্ম যা বেস স্তর উপাদানগুলি ব্যবহার করে এবং সহজ রোলব্যাকের অনুমতি দেয়।",
      "ব্যবহারকারীদের ব্লুফিনের সাথে ইতিবাচক অভিজ্ঞতা রয়েছে এবং ওয়েবসাইট ডিজাইন এবং পারফরম্যান্সের তাত্পর্য নিয়ে আলোচনা করে।",
      "ব্লুফিন অন্যান্য অপারেটিং সিস্টেমের সাথে তুলনা করা হয় এবং প্রধান উন্নয়ন মেশিনগুলিতে ব্যবহারের জন্য সুপারিশ করা হয়।"
    ],
    "points": 178,
    "commentCount": 66,
    "retryCount": 0,
    "time": 1705253010
  },
  {
    "id": 38996120,
    "title": "ফেডেক্স অ্যামাজনের সাথে প্রতিযোগিতা করার জন্য একটি এন্ড-টু-এন্ড ই-কমার্স প্ল্যাটফর্ম এফডিএক্স চালু করেছে",
    "originLink": "https://www.theverge.com/2024/1/14/24038042/fedex-fdx-e-commerce-platform-amazon-rival-shoprunner",
    "originBody": "",
    "commentLink": "https://news.ycombinator.com/item?id=38996120",
    "commentBody": "",
    "originSummary": [
      "অনলাইন মার্চেন্টদের তাদের সাপ্লাই চেইন পরিচালনা, গ্রাহকদের কাছে বিক্রয় এবং ডেলিভারি পরিচালনায় সহায়তা করার জন্য ফেডএক্স এফডিএক্স নামে একটি নতুন ই-কমার্স প্ল্যাটফর্ম চালু করছে।",
      "প্ল্যাটফর্মটি বিদ্যমান ফেডেক্স সরঞ্জামগুলিকে নতুন বৈশিষ্ট্যগুলির সাথে একত্রিত করবে, যেমন \"কাস্টম পোস্ট-ক্রয় অভিজ্ঞতা\", যা ব্র্যান্ডগুলিকে সুনির্দিষ্ট চালানের বিবরণ সরবরাহ করতে এবং অর্ডার পরিচালনার জন্য ফেডেক্সের শিপমেন্ট নেটওয়ার্ক ডেটা নিয়োগ করতে সক্ষম করে।",
      "এই উন্নয়নটি লজিস্টিক সেক্টরে অ্যামাজনের সাথে ফেডেক্সের প্রতিযোগিতার প্রতিক্রিয়া, যেখানে ফেডএক্স চ্যালেঞ্জের মুখোমুখি হয়েছে এবং নতুন প্ল্যাটফর্মের ক্ষমতাগুলি কাজে লাগিয়ে তার প্রতিযোগিতামূলকতা বজায় রাখার লক্ষ্য নিয়েছে।"
    ],
    "commentSummary": [
      "অ্যামাজনের প্রভাবশালী লজিস্টিক এবং অনলাইন শপিং পরিষেবাগুলির সাথে প্রতিযোগিতা করার জন্য ফেডেক্স একটি ই-কমার্স প্ল্যাটফর্ম চালু করেছে।",
      "ব্যবহারকারীরা অ্যামাজনের ওয়েবসাইট, মূল্য নির্ধারণ এবং বিক্রেতার অভিজ্ঞতা নিয়ে হতাশা প্রকাশ করেছেন, যার ফলে বিকল্প বিকল্পগুলির চাহিদা তৈরি হয়েছে।",
      "ফেডএক্স শপিং কার্ট প্লাগইন, কেন্দ্রীভূত অর্ডার, পেমেন্ট এবং লজিস্টিক পরিষেবাগুলিকে একীভূত করে একটি বিস্তৃত ব্যবসায়িক সমাধান সরবরাহ করার লক্ষ্য রাখে। যাইহোক, অ্যামাজনের সাথে প্রতিযোগিতা করার তাদের ক্ষমতা সম্পর্কে উদ্বেগ রয়েছে, বিশেষত তাদের ডেলিভারি পরিষেবা এবং নির্ভুলতা সম্পর্কে।"
    ],
    "points": 160,
    "commentCount": 110,
    "retryCount": 0,
    "time": 1705280137
  },
  {
    "id": 38992689,
    "title": "উপাদান ফাইল প্রবর্তন: উপাদান ডিজাইন সহ অ্যান্ড্রয়েডের জন্য একটি ওপেন সোর্স ফাইল ম্যানেজার",
    "originLink": "https://github.com/zhanghai/MaterialFiles",
    "originBody": "",
    "commentLink": "https://news.ycombinator.com/item?id=38992689",
    "commentBody": "",
    "originSummary": [
      "এই ওপেন-সোর্স ফাইল ম্যানেজারটি উপাদান নকশা নির্দেশিকা অনুসরণ করে হালকা এবং সুরক্ষিত হওয়ার জন্য ডিজাইন করা হয়েছে।",
      "এটি ব্রেডক্রাম্বগুলির সাথে ফাইল সিস্টেমের মাধ্যমে সহজ নেভিগেশন সরবরাহ করে এবং রুট অ্যাক্সেসের সাথে ফাইলগুলি পরিচালনা করতে সহায়তা করে।",
      "এতে সংকুচিত ফাইলগুলি দেখা এবং তৈরি করা এবং এফটিপি, এসএফটিপি এবং এসএমবি সার্ভারগুলিতে ফাইলগুলি পরিচালনা করার বৈশিষ্ট্যও রয়েছে। ইউজার ইন্টারফেসটি নাইট মোড বিকল্প সহ বিভিন্ন রঙের থিম দিয়ে কাস্টমাইজ করা যেতে পারে।"
    ],
    "commentSummary": [
      "উপাদান ফাইলগুলি অ্যান্ড্রয়েডের জন্য একটি ওপেন-সোর্স ফাইল ম্যানেজার যা উপাদান নকশা নীতিগুলি মেনে চলে, একটি দৃশ্যমান আকর্ষণীয় এবং স্বজ্ঞাত ব্যবহারকারীর অভিজ্ঞতা সরবরাহ করে।",
      "এটিতে সহজ নেভিগেশন, রুট অ্যাক্সেসের জন্য সমর্থন, আর্কাইভগুলি পরিচালনা করার ক্ষমতা এবং এফটিপি, এসএফটিপি এবং এসএমবি সার্ভারগুলিতে ফাইলগুলি পরিচালনা করার ক্ষমতার মতো বিভিন্ন বৈশিষ্ট্য রয়েছে।",
      "ব্যবহারকারীরা এর কার্যকারিতা এবং এটি গোপনীয়তা-কেন্দ্রিক এফড্রয়েড অ্যাপ স্টোর থেকে ডাউনলোড করা যেতে পারে, আরও নিরাপদ অভিজ্ঞতা নিশ্চিত করে।"
    ],
    "points": 136,
    "commentCount": 62,
    "retryCount": 0,
    "time": 1705255599
  },
  {
    "id": 38993552,
    "title": "গেম ইঞ্জিনগুলির জন্য দ্রুত আরআইএসসি-ভি-ভিত্তিক স্ক্রিপ্টিং সিস্টেম: উন্নত কর্মক্ষমতা এবং হ্রাস ওভারহেড",
    "originLink": "https://github.com/fwsGonzo/rvscript",
    "originBody": "",
    "commentLink": "https://news.ycombinator.com/item?id=38993552",
    "commentBody": "",
    "originSummary": [
      "আরভিস্ক্রিপ্ট একটি গেম ইঞ্জিন স্ক্রিপ্টিং সিস্টেম যা টাইপ-নিরাপদ এবং মেমরি-নিরাপদ স্ক্রিপ্টের জন্য একটি কম লেটেন্সি আরআইএসসি-ভি স্যান্ডবক্স ব্যবহার করে।",
      "এর লক্ষ্য হ'ল পারফরম্যান্স বাড়ানো এবং গেম স্ক্রিপ্টিংয়ে ফাংশন কলগুলির ওভারহেড হ্রাস করা।",
      "প্রকল্পটিতে স্ক্রিপ্ট এক্সিকিউশন অপ্টিমাইজ করার জন্য উন্নত কৌশলগুলি বাস্তবায়নের জন্য উদাহরণ এবং বেঞ্চমার্ক অন্তর্ভুক্ত রয়েছে এবং নতুন কার্যকারিতা যুক্ত করার জন্য গতিশীল কলগুলিকে সমর্থন করার জন্য একটি আরআইএসসি-ভি কম্পাইলারের সাথে ব্যবহার করা যেতে পারে। যাইহোক, স্থিতিশীল এপিআই এখনও উপলব্ধ নয় কারণ সিস্টেমটি এখনও বিকাশে রয়েছে।"
    ],
    "commentSummary": [
      "গিটহাব আলোচনায় গেম ইঞ্জিনগুলির জন্য স্ক্রিপ্টিং ব্যাক এন্ড হিসাবে আরআইএসসি-ভি ব্যবহারের উপর দৃষ্টি নিবদ্ধ করা হয়েছে, লেখক বুদ্ধিবৃত্তিক উদ্দীপনা এবং সংক্ষিপ্ত বিকাশের সময়ের মতো সুবিধাগুলি তুলে ধরেছেন।",
      "আলোচনায় অন্যান্য অংশগ্রহণকারীদের দ্বারা সম্ভাব্য বিলম্বসমস্যা এবং বিকল্প কম্পাইলার লক্ষ্য সম্পর্কে উদ্বেগ উত্থাপিত হয়।",
      "আরআইএসসি-ভি এর পছন্দটি অন্যান্য আর্কিটেকচারের সাথে উত্তরাধিকার সামঞ্জস্যতা এবং সম্ভাব্য পেটেন্ট সীমাবদ্ধতার অভাবের জন্য দায়ী, যখন সিপিইউ-বাউন্ড কোডের জন্য ভার্চুয়ালাইজেশন এবং স্যান্ডবক্সিং প্রযুক্তিগুলি অন্বেষণ করা হয়।",
      "পারফরম্যান্সের ক্ষেত্রে লুয়া এবং লুয়াজেআইটি, ওয়েবঅ্যাসেম্বলি এবং সি / সি ++ এর মতো স্ক্রিপ্টিং ভাষাগুলির মধ্যে তুলনা করা হয়।",
      "আরআইএসসি-ভি ব্যবহার করে একটি মেশিন কোড দোভাষীর বাস্তবায়ন নিয়ে আলোচনা করা হয়েছে, পাশাপাশি নিম, নেলুয়া, জিগ, রাস্ট এবং কোটলিনের মতো ভাষা ব্যবহার করে আরআইএসসি-ভি তে সংকলন করার জন্য বিবেচনা করা হয়েছে।",
      "গেম ইঞ্জিন স্ক্রিপ্টিংয়ের জন্য সি / সি ++ এবং জাভাস্ক্রিপ্ট, কোটলিন এবং সি # এর মতো উচ্চ-স্তরের ভাষাগুলির ব্যবহারও কভার করা হয়েছে, পারফরম্যান্স এবং সামঞ্জস্যতার উপর দৃষ্টি নিবদ্ধ করে।",
      "নিরাপদ সার্ভার-সাইড কোড সম্পাদনের জন্য আরআইএসসি-ভি এর সম্ভাব্য ব্যবহার, ওয়েবঅ্যাসেম্বলির ব্যাখ্যা করার চ্যালেঞ্জ এবং স্ট্যাক মেশিনগুলি ব্যাখ্যা করার জন্য একটি রেজিস্টার অ্যালোকেটার / ফাইল বাস্তবায়নও আলোচনার বিষয়।",
      "স্ট্যাক মেশিন এবং রেজিস্টার মেশিনগুলির মধ্যে পার্থক্য, পাশাপাশি ব্রাউজার ইঞ্জিনগুলির জন্য ওয়েবঅ্যাসেম্বলির অপ্টিমাইজেশন, সংক্ষিপ্তভাবে উল্লেখ করা হয়েছে।",
      "আলোচনাটি সংক্ষিপ্তভাবে আরআইএসসি-ভি আর্কিটেকচারে মান যুক্ত করার প্রক্রিয়া এবং আরআইএসসি-ভি এর ক্রমবর্ধমান জনপ্রিয়তাকে স্পর্শ করে।"
    ],
    "points": 135,
    "commentCount": 70,
    "retryCount": 0,
    "time": 1705260286
  },
  {
    "id": 38990709,
    "title": "ট্রান্সফরমার আর্কিটেকচার এবং ভাষা মডেলগুলির জন্য পাইথন এবং পাইটর্চে মনোযোগ প্রক্রিয়া বাস্তবায়ন",
    "originLink": "https://magazine.sebastianraschka.com/p/understanding-and-coding-self-attention",
    "originBody": "",
    "commentLink": "https://news.ycombinator.com/item?id=38990709",
    "commentBody": "",
    "originSummary": [
      "এই নিবন্ধটি ট্রান্সফরমার আর্কিটেকচার এবং বৃহত ভাষা মডেলগুলির জন্য পাইথন এবং পাইটর্চে স্ব-মনোযোগ প্রক্রিয়াগুলি কীভাবে প্রয়োগ করা যায় তা প্রদর্শন করে।",
      "এটি প্রাকৃতিক ভাষা প্রক্রিয়াকরণের কাজগুলিতে মনোযোগ প্রক্রিয়াগুলির গুরুত্ব ব্যাখ্যা করে এবং বিভিন্ন ধরণের মনোযোগ প্রক্রিয়াগুলি অন্বেষণ করে।",
      "নিবন্ধটি স্ব-মনোযোগ এবং কার্যকারণ স্ব-মনোযোগে বাক্য এম্বেডিং, কম্পিউটিং মনোযোগ ওজন এবং প্রসঙ্গ ভেক্টর তৈরির প্রক্রিয়াটি কভার করে। এটি মনোযোগ ওজন স্বাভাবিক করার তাৎপর্যকেও তুলে ধরে।"
    ],
    "commentSummary": [
      "নিবন্ধটি কোডিংয়ে ব্যবহৃত বিভিন্ন মনোযোগ প্রক্রিয়াগুলি যেমন স্ব-মনোযোগ, মাল্টি-হেড মনোযোগ, ক্রস-মনোযোগ এবং কার্যকারণ-মনোযোগ অন্বেষণ করে।",
      "ভাষা মডেলগুলি প্রশিক্ষণের জন্য ফ্ল্যাশ মনোযোগের মতো অপ্টিমাইজড বাস্তবায়নগুলি সুপারিশ করা হয়।",
      "ব্যবহারকারীরা পাইটর্চে পাওয়া যায় না এমন মনোযোগ পদ্ধতিবাস্তবায়নের সম্ভাবনা এবং নিউরাল নেটওয়ার্কগুলিতে মনোযোগ এবং মানব মনোবিজ্ঞানে মনোযোগের মধ্যে সংযোগ নিয়ে আলোচনা করে।"
    ],
    "points": 130,
    "commentCount": 9,
    "retryCount": 0,
    "time": 1705242587
  },
  {
    "id": 38991953,
    "title": "রাফল: 2023 সালে বড় উন্নতির সাথে ফ্ল্যাশ এমুলেটর অগ্রগতি",
    "originLink": "https://ruffle.rs/blog/2024/01/14/2023-in-review",
    "originBody": "",
    "commentLink": "https://news.ycombinator.com/item?id=38991953",
    "commentBody": "",
    "originSummary": [
      "রাফল, একটি ফ্ল্যাশ এমুলেটর, অ্যাকশনস্ক্রিপ্ট 3 ভাষা এবং এপিআইতে একাধিক উন্নতিসহ 2023 সালে যথেষ্ট অগ্রগতি অর্জন করেছে।",
      "এমুলেটরটি এখন ফিল্টার, ক্যাশঅ্যাসবিটম্যাপ, টেক্সট রেন্ডারিং, সকেট, ফ্ল্যাশ রিমোটিং, এফএলভি এবং ভিডিও প্লেব্যাক ক্ষমতা সমর্থন করে।",
      "এক্সটেনশন, ডেস্কটপ ইউআই এবং ওয়েবসাইটের উন্নতির পাশাপাশি অবদান এবং স্পনসরশিপ সমর্থনসহ এআইআর এবং মিশ্র এভিএম চলচ্চিত্রগুলির জন্য প্রাথমিক সমর্থন যুক্ত করা হয়েছে।"
    ],
    "commentSummary": [
      "পোস্টটি রাফল প্রকল্পকে তুলে ধরেছে, যার লক্ষ্য ফ্ল্যাশ প্রযুক্তিকে পুনরুজ্জীবিত করা এবং এর সাথে যুক্ত নস্টালজিয়া এবং সৃজনশীলতা ফিরিয়ে আনা।",
      "ব্যবহারকারীরা ফ্ল্যাশ সরবরাহ করা অনন্য উন্নয়ন অভিজ্ঞতা এবং ইন্টারেক্টিভ সামগ্রীর জন্য তাদের আকাঙ্ক্ষা প্রকাশ করে।",
      "গেম ইঞ্জিন বা ফ্লাটারের মতো বিকল্প প্রযুক্তির প্রস্তাব দেওয়া হয়েছে, তবে সর্বসম্মতি হ'ল ব্রাউজারে ফ্ল্যাশ ফিরিয়ে আনার প্রচেষ্টার জন্য রাফল প্রশংসনীয়।"
    ],
    "points": 127,
    "commentCount": 20,
    "retryCount": 0,
    "time": 1705250684
  },
  {
    "id": 38991248,
    "title": "ইএসপি 32 রিভার্স ইঞ্জিনিয়ারিংয়ের জন্য একটি কার্যকর ফ্যারাডে খাঁচা তৈরি করা",
    "originLink": "https://esp32-open-mac.be/posts/0003-faraday-cage/",
    "originBody": "",
    "commentLink": "https://news.ycombinator.com/item?id=38991248",
    "commentBody": "",
    "originSummary": [
      "আশেপাশের বাতাসে উচ্চ পরিমাণে ওয়াই-ফাই প্যাকেটের কারণে লেখক ইএসপি 32 মাইক্রোকন্ট্রোলারের জন্য ওয়াই-ফাই স্ট্যাকের বিপরীত প্রকৌশলে চ্যালেঞ্জের মুখোমুখি হন।",
      "প্রচলিত পদ্ধতি, যেমন পেইন্ট টিন, ফেরাইট চোকস এবং ফ্যারাডে খাঁচা হিসাবে বন্ধ মাইক্রোওয়েভ ব্যবহার করা, বাইরের প্যাকেটগুলি ব্লক করতে অকার্যকর প্রমাণিত হয়।",
      "লেখক একটি গবেষণা পত্র আবিষ্কার করেছেন যা পরিবাহী ফ্যাব্রিক এবং সাধারণভাবে উপলব্ধ উপকরণ থেকে তৈরি একটি সাশ্রয়ী মূল্যের ফ্যারাডে খাঁচার রূপরেখা দেয়।",
      "খরচ কমাতে, লেখক কাঠের ক্যাবিনেট এবং একটি সীসা-অ্যাসিড ব্যাটারি ব্যবহার করে ফ্যারাডে খাঁচা তৈরি করার পরিকল্পনা করেছেন।",
      "নির্মিত ফ্যারাডে খাঁচা সফলভাবে আরএফ সংকেতগুলি ব্লক করে, ওয়াই-ফাই স্ট্যাকের আরও সঠিক বিশ্লেষণের অনুমতি দেয়।",
      "সারসংক্ষেপে সিগন্যাল অ্যাটেনশন, উপকরণের একটি বিল এবং ফ্যারাডে খাঁচা নির্মাণের জন্য বিস্তারিত নির্দেশাবলী অন্তর্ভুক্ত রয়েছে।"
    ],
    "commentSummary": [
      "পোস্টটি ইএসপি 32 রিভার্স ইঞ্জিনিয়ারিংয়ের জন্য ডেটা পাসথ্রু সহ একটি ফ্যারাডে খাঁচা নির্মাণের অন্বেষণ করে।",
      "খাঁচার জন্য প্রস্তাবিত উপকরণগুলি হ'ল পাসথ্রুয়ের জন্য ইকোফয়েল এনটি এবং ডেল্টা 20 ডিবিএজি 5।",
      "পোস্টটিতে উইন্ডোজ / ভেন্টগুলির জন্য সুপারিশগুলি, শিল্ডিংয়ের জন্য উপাদান কার্যকারিতা, আরএফ পরীক্ষা, ওয়াইফাই সংযোগ ের সমস্যা এবং সুরক্ষার জন্য মাইক্রোওয়েভ ওভেনের সম্ভাব্য ব্যবহারও অন্তর্ভুক্ত রয়েছে।"
    ],
    "points": 118,
    "commentCount": 25,
    "retryCount": 0,
    "time": 1705246161
  },
  {
    "id": 38991392,
    "title": "ক্রিস্টাল 1.11.0: নতুন বৈশিষ্ট্য, বাগ ফিক্স এবং এলএলভিএম 18 সমর্থন",
    "originLink": "https://crystal-lang.org/2024/01/08/1.11.0-released/",
    "originBody": "",
    "commentLink": "https://news.ycombinator.com/item?id=38991392",
    "commentBody": "",
    "originSummary": [
      "ক্রিস্টাল প্রোগ্রামিং ল্যাঙ্গুয়েজ বিভিন্ন নতুন ফিচার এবং বাগ ফিক্স সহ একটি নতুন সংস্করণ প্রকাশ করেছে।",
      "উল্লেখযোগ্য পরিবর্তনগুলির মধ্যে আসন্ন এলএলভিএম 18 এর জন্য সমর্থন, কম্পাইলার অপ্টিমাইজেশান স্তর, নতুন অ্যালাইনমেন্ট আদিমএবং উইন্ডোজে গতিশীল লিঙ্ক লাইব্রেরিগুলি নির্দিষ্ট করার জন্য একটি প্যারামিটার অন্তর্ভুক্ত রয়েছে।",
      "রিলিজে সংগ্রহ পদ্ধতি, সংখ্যাগত ক্রিয়াকলাপ, পাঠ্য প্রক্রিয়াকরণ এবং বাগ সংশোধনের পাশাপাশি কাস্টম বরাদ্দ প্রক্রিয়া সম্পর্কিত পরীক্ষামূলক বৈশিষ্ট্যগুলির জন্য উন্নতিও অন্তর্ভুক্ত রয়েছে।",
      "ম্যাক্রো এক্সপ্রেশন এবং নির্দিষ্ট এলএলভিএম ফাংশনগুলিতে স্প্ল্যাট অপারেটরগুলি অবমূল্যায়ন করা হয়।",
      "স্পন্সরদের সহায়তায় মুক্তি দেওয়া সম্ভব হয়েছে।"
    ],
    "commentSummary": [
      "উইন্ডোজ সমর্থন সম্পর্কিত চলমান আলোচনার উপর ফোকাস করে ক্রিস্টাল সংস্করণ 1.11.0 প্রকাশ করা হয়েছে।",
      "ক্রিস্টাল ডেভেলপাররা উইন্ডোজ সমর্থনকে অগ্রাধিকার দিচ্ছে এবং সক্রিয়ভাবে এর উন্নয়নে অবদান রাখছে এবং আর্থিক সহায়তা দিচ্ছে।",
      "উইন্ডোজে ক্রিস্টালের চাহিদা রয়েছে, বিশেষত সম্পূর্ণ পোর্টেবল এক্সিকিউটেবল ফাইল তৈরির জন্য। ক্রিস্টাল একটি স্থিরভাবে টাইপ করা এবং সংকলিত প্রোগ্রামিং ভাষা যা পাইথন এবং রুবির মতো ব্যাখ্যা করা ভাষাগুলির সরলতার সাথে গো এবং রাস্টের গতিকে একত্রিত করে। এটি সি প্রোগ্রামগুলির সাথে ইন্টারঅপারেবিলিটি সরবরাহ করে এবং রুবি বা পাইথনের চেয়ে ভাল টাইপিং এবং কম মেমরি ব্যবহার সরবরাহ করে।"
    ],
    "points": 107,
    "commentCount": 58,
    "retryCount": 0,
    "time": 1705246909
  },
  {
    "id": 38991521,
    "title": "চ্যালেঞ্জিং ইনসুলিন থেরাপি: গ্যারি টাউবসের সাথে ডায়াবেটিস পুনর্বিবেচনা",
    "originLink": "https://www.theguardian.com/society/2024/jan/14/unlocking-the-truth-about-diabetes-is-it-time-for-a-diet-based-treatment",
    "originBody": "",
    "commentLink": "https://news.ycombinator.com/item?id=38991521",
    "commentBody": "",
    "originSummary": [
      "বিজ্ঞান লেখক গ্যারি টাউবস ডায়াবেটিসের চিকিত্সা সম্পর্কে মূলধারার দৃষ্টিভঙ্গিকে চ্যালেঞ্জ করেছেন এবং পরামর্শ দিয়েছেন যে ইনসুলিন থেরাপি এই রোগের বৈশ্বিক মহামারীতে অবদান রাখতে পারে।",
      "টাউবস ডায়াবেটিসে রক্তে গ্লুকোজের মাত্রা পরিচালনার বিকল্প হিসাবে কেটোর মতো লো-কার্ব ডায়েটের পক্ষে।",
      "তার মতামত প্রশংসা এবং সমালোচনা উভয়ই উত্থাপন করেছে, কেউ কেউ পুষ্টি সম্পর্কে তার গবেষণার প্রশংসা করেছে, অন্যরা লো-কার্ব ডায়েটের সুরক্ষা এবং কার্যকারিতা নিয়ে প্রশ্ন তুলেছে।"
    ],
    "commentSummary": [
      "আলোচনাটি পুষ্টি, ডায়াবেটিস পরিচালনা, ওজন হ্রাস এবং পুষ্টি বিজ্ঞানের নির্ভরযোগ্যতার বিভিন্ন দিক অন্বেষণ করে।",
      "লো-কার্ব ডায়েট, বিভিন্ন ধরণের ডায়াবেটিস এবং রক্তে গ্লুকোজের মাত্রা ট্র্যাক করার তাত্পর্য সম্পর্কে বিভিন্ন মতামত ভাগ করা হয়।",
      "কথোপকথনটি ডায়াবেটিস পরিচালনায় ডায়েটের ভূমিকা এবং বিভিন্ন ডায়েটরি পদ্ধতির সম্ভাব্য সুবিধাগুলি নিয়েও আলোচনা করে, পাশাপাশি পুষ্টি বিজ্ঞানের বৈজ্ঞানিক বৈধতা এবং এই ক্ষেত্রের বিশেষজ্ঞদের যোগ্যতা নিয়েও আলোচনা করে।"
    ],
    "points": 106,
    "commentCount": 107,
    "retryCount": 0,
    "time": 1705247634
  },
  {
    "id": 38991317,
    "title": "মেক্সিকো পানামা খালের প্রতিদ্বন্দ্বী রেলপথ নির্মাণ করছে",
    "originLink": "https://www.japantimes.co.jp/business/2023/11/16/mexico-rail-rival-panama-canal/",
    "originBody": "",
    "commentLink": "https://news.ycombinator.com/item?id=38991317",
    "commentBody": "",
    "originSummary": [
      "মেক্সিকান সরকার পানামা খালের সাথে প্রতিযোগিতা করার জন্য একটি রেলপথ নির্মাণ করছে, যা প্রশান্ত মহাসাগর এবং আটলান্টিক মহাসাগরকে তাদের সংকীর্ণতম পয়েন্টে সংযুক্ত করে।",
      "প্রকল্পটি অর্থনৈতিক সুবিধা বয়ে আনবে বলে আশা করা হচ্ছে, তবে সম্ভাব্য পরিবেশগত এবং সামাজিক পরিণতি সম্পর্কে ক্রমবর্ধমান উদ্বেগ রয়েছে।",
      "রাষ্ট্রপতি আন্দ্রেস ম্যানুয়েল লোপেজ ওব্রাদোরের প্রশাসনের সময় ২০২০ সালে রেলপথের নির্মাণ কাজ শুরু হয়েছিল।"
    ],
    "commentSummary": [
      "মেক্সিকো পানামা খালে পরিবহন এবং জলের ঘাটতি সমস্যা সমাধানের বিকল্প হিসাবে একটি রেল ব্যবস্থা নির্মাণ করছে।",
      "সামুদ্রিক রুটের তুলনায় রেল ব্যবস্থার ব্যয় এবং দক্ষতা সম্পর্কে উদ্বেগ উত্থাপিত হয়েছে, যা কানাডার চারপাশে উত্তরে যাওয়ার মতো বিকল্প রুট ব্যবহারের পরামর্শ দেয়।",
      "আলোচিত বিভিন্ন সমাধানের মধ্যে রয়েছে উন্নত বাছাই কৌশল, সমান্তরাল রেলপথ এবং স্কেল-আপ ক্রলার ট্রান্সপোর্টার, তবে জাহাজের উপর চাপ, দুর্ঘটনা এবং জল দূষণ সম্পর্কে উদ্বেগ রয়ে গেছে।",
      "অন্যান্য প্রস্তাবিত সমাধানগুলির মধ্যে রয়েছে বিদ্যমান তালা ব্যবহার করা, সমুদ্র থেকে জল পাম্প করা এবং টানেল তৈরি করা।",
      "পানামা খালে পানির স্তর কম থাকায় স্টোল্ট-নিয়েলসেন নামের একটি ট্যাংকার বিভাগ সুয়েজ খালে জাহাজ চলাচল করছে।",
      "মিঠা পানির সরবরাহের পরিপূরক হিসাবে লবণাক্ত জল এবং মডুলার পারমাণবিক চুল্লি ব্যবহারের সম্ভাব্যতা বিবেচনা করা হচ্ছে।",
      "মিঠা পানির হ্রদে লবণাক্ত পানি পাম্পিং নিয়ে বিতর্ক রয়েছে, বাস্তুতন্ত্রের ক্ষতি হ্রাস এবং সৌর বা জলবিদ্যুৎ শক্তি ব্যবহার করে একটি সিস্টেম বাস্তবায়নের সম্ভাব্যতা এবং ব্যয় নিয়ে আলোচনা রয়েছে।"
    ],
    "points": 94,
    "commentCount": 101,
    "retryCount": 0,
    "time": 1705246507
  }
]
